{
  "1_day_nav_change": "USD 0.68 (4.27%)",
  "3y_beta": "0.997",
  "52w_high": 16.7,
  "52w_low": 6.26,
  "administrator": "State Street Fund Services (Ireland) Limited",
  "asset_class": "Equity",
  "base_currency": "USD",
  "benchmark_index": "MSCI ACWI IMI Semiconductors & Semiconductor Equipment ESG Screened Capped",
  "benchmark_level": "USD 14,567.42",
  "benchmark_ticker": "NU738380",
  "bloomberg_ticker": "INAVSEM3",
  "custodian": "State Street Custodial Services (Ireland) Limited",
  "date": "2026-04-24",
  "domicile": "Ireland",
  "fiscal_year_end": "31 May",
  "fund_launch_date": "03-Aug-21",
  "fund_manager": "BlackRock Asset Management Ireland Limited",
  "holdings": [
    {
      "name": "ACM RESEARCH (SHANGHAI) INC A",
      "ticker": "688082",
      "weight": 0.00373,
      "shares_held": 5695,
      "exchange": "Shanghai Stock Exchange",
      "price": 23.11
    },
    {
      "name": "ACM RESEARCH CLASS A INC",
      "ticker": "ACMR",
      "weight": 0.04263,
      "shares_held": 26828,
      "exchange": "NASDAQ",
      "price": 56.1
    },
    {
      "name": "ADATA TECHNOLOGY LTD",
      "ticker": "3260",
      "weight": 0.04805,
      "shares_held": 133473,
      "exchange": "Gretai Securities Market",
      "price": 12.71
    },
    {
      "name": "ADVANCED ECHEM MATERIALS LTD",
      "ticker": "4749",
      "weight": 0.02822,
      "shares_held": 32000,
      "exchange": "Gretai Securities Market",
      "price": 31.14
    },
    {
      "name": "ADVANCED MICRO DEVICES INC",
      "ticker": "AMD",
      "weight": 6.16084,
      "shares_held": 625372,
      "exchange": "NASDAQ",
      "price": 347.81
    },
    {
      "name": "ADVANCED MICRO-FABRICATION EQUIPME",
      "ticker": "688012",
      "weight": 0.02543,
      "shares_held": 18977,
      "exchange": "Shanghai Stock Exchange",
      "price": 47.31
    },
    {
      "name": "ADVANCED WIRELESS SEMICONDUCTOR",
      "ticker": "8086",
      "weight": 0.01279,
      "shares_held": 103000,
      "exchange": "Gretai Securities Market",
      "price": 4.38
    },
    {
      "name": "ADVANTEST CORP",
      "ticker": "6857",
      "weight": 1.94371,
      "shares_held": 371800,
      "exchange": "Tokyo Stock Exchange",
      "price": 184.57
    },
    {
      "name": "AEHR TEST SYSTEMS",
      "ticker": "AEHR",
      "weight": 0.03938,
      "shares_held": 14496,
      "exchange": "NASDAQ",
      "price": 95.91
    },
    {
      "name": "AIROHA TECHNOLOGY CORP",
      "ticker": "6526",
      "weight": 0.00541,
      "shares_held": 10000,
      "exchange": "Taiwan Stock Exchange",
      "price": 19.1
    },
    {
      "name": "AIXTRON",
      "ticker": "AIXA",
      "weight": 0.08716,
      "shares_held": 56449,
      "exchange": "Xetra",
      "price": 54.52
    },
    {
      "name": "ALCHIP TECHNOLOGIES LTD",
      "ticker": "3661",
      "weight": 0.14036,
      "shares_held": 37000,
      "exchange": "Taiwan Stock Exchange",
      "price": 133.93
    },
    {
      "name": "ALLEGRO MICROSYSTEMS INC",
      "ticker": "ALGM",
      "weight": 0.08448,
      "shares_held": 67584,
      "exchange": "NASDAQ",
      "price": 44.13
    },
    {
      "name": "ALPHA AND OMEGA SEMICONDUCTOR LTD",
      "ticker": "AOSL",
      "weight": 0.01739,
      "shares_held": 13814,
      "exchange": "NASDAQ",
      "price": 44.45
    },
    {
      "name": "AMBARELLA INC",
      "ticker": "AMBA",
      "weight": 0.04159,
      "shares_held": 21959,
      "exchange": "NASDAQ",
      "price": 66.87
    },
    {
      "name": "AMKOR TECHNOLOGY INC",
      "ticker": "AMKR",
      "weight": 0.1399,
      "shares_held": 63244,
      "exchange": "NASDAQ",
      "price": 78.1
    },
    {
      "name": "AMLOGIC (SHANGHAI) LTD A",
      "ticker": "688099",
      "weight": 0.00194,
      "shares_held": 5148,
      "exchange": "Shanghai Stock Exchange",
      "price": 13.33
    },
    {
      "name": "AMS-OSRAM AG",
      "ticker": "AMS",
      "weight": 0.02032,
      "shares_held": 48450,
      "exchange": "SIX Swiss Exchange",
      "price": 14.81
    },
    {
      "name": "ANALOG DEVICES INC",
      "ticker": "ADI",
      "weight": 2.69753,
      "shares_held": 238349,
      "exchange": "NASDAQ",
      "price": 399.57
    },
    {
      "name": "AP MEMORY TECHNOLOGY CORP",
      "ticker": "6531",
      "weight": 0.02979,
      "shares_held": 42000,
      "exchange": "Taiwan Stock Exchange",
      "price": 25.04
    },
    {
      "name": "APPLIED MATERIAL INC",
      "ticker": "AMAT",
      "weight": 4.17664,
      "shares_held": 353582,
      "exchange": "NASDAQ",
      "price": 417.04
    },
    {
      "name": "ARDENTEC CORP",
      "ticker": "3264",
      "weight": 0.04423,
      "shares_held": 234000,
      "exchange": "Gretai Securities Market",
      "price": 6.67
    },
    {
      "name": "ASE TECHNOLOGY HOLDING LTD",
      "ticker": "3711",
      "weight": 0.73031,
      "shares_held": 1636000,
      "exchange": "Taiwan Stock Exchange",
      "price": 15.76
    },
    {
      "name": "ASM INTERNATIONAL NV",
      "ticker": "ASM",
      "weight": 0.65558,
      "shares_held": 22795,
      "exchange": "Euronext Amsterdam",
      "price": 1015.38
    },
    {
      "name": "ASMEDIA TECHNOLOGY INC",
      "ticker": "5269",
      "weight": 0.01677,
      "shares_held": 14390,
      "exchange": "Taiwan Stock Exchange",
      "price": 41.15
    },
    {
      "name": "ASML HOLDING NV",
      "ticker": "ASML",
      "weight": 6.18837,
      "shares_held": 149361,
      "exchange": "Euronext Amsterdam",
      "price": 1462.79
    },
    {
      "name": "ASMPT LTD",
      "ticker": "522",
      "weight": 0.09264,
      "shares_held": 155100,
      "exchange": "Hong Kong Exchanges And Clearing Ltd",
      "price": 21.09
    },
    {
      "name": "ASPEED TECHNOLOGY INC",
      "ticker": "5274",
      "weight": 0.20128,
      "shares_held": 13662,
      "exchange": "Gretai Securities Market",
      "price": 520.15
    },
    {
      "name": "ASTERA LABS INC",
      "ticker": "ALAB",
      "weight": 0.3941,
      "shares_held": 65373,
      "exchange": "NASDAQ",
      "price": 212.84
    },
    {
      "name": "AUD CASH",
      "ticker": "AUD",
      "weight": 0.00062,
      "shares_held": 30458,
      "exchange": "-",
      "price": 71.41
    },
    {
      "name": "AXCELIS TECHNOLOGIES INC",
      "ticker": "ACLS",
      "weight": 0.06531,
      "shares_held": 16109,
      "exchange": "NASDAQ",
      "price": 143.13
    },
    {
      "name": "BE SEMICONDUCTOR INDUSTRIES NV",
      "ticker": "BESI",
      "weight": 0.29777,
      "shares_held": 35610,
      "exchange": "Euronext Amsterdam",
      "price": 295.23
    },
    {
      "name": "BESTECHNIC (SHANGHAI) LTD A",
      "ticker": "688608",
      "weight": 0.00245,
      "shares_held": 3530,
      "exchange": "Shanghai Stock Exchange",
      "price": 24.47
    },
    {
      "name": "BLACK SESAME INTERNATIONAL HOLDING",
      "ticker": "2533",
      "weight": 0.00476,
      "shares_held": 78900,
      "exchange": "Hong Kong Exchanges And Clearing Ltd",
      "price": 2.13
    },
    {
      "name": "BLK ICS USD LIQ AGENCY DIS",
      "ticker": "ICSUAGD",
      "weight": 0.05667,
      "shares_held": 2000928,
      "exchange": "-",
      "price": 1
    },
    {
      "name": "BOROSIL RENEWABLES LTD",
      "ticker": "BORORENEW",
      "weight": 0.00368,
      "shares_held": 23976,
      "exchange": "National Stock Exchange Of India",
      "price": 5.42
    },
    {
      "name": "BROADCOM INC",
      "ticker": "AVGO",
      "weight": 7.62014,
      "shares_held": 636370,
      "exchange": "NASDAQ",
      "price": 422.76
    },
    {
      "name": "CAMBRICON TECHNOLOGIES CORPORATION",
      "ticker": "688256",
      "weight": 0.0563,
      "shares_held": 10045,
      "exchange": "Shanghai Stock Exchange",
      "price": 197.88
    },
    {
      "name": "CAMTEK LTD",
      "ticker": "CAMT",
      "weight": 0.08385,
      "shares_held": 14592,
      "exchange": "Tel Aviv Stock Exchange",
      "price": 202.87
    },
    {
      "name": "CASH COLLATERAL USD MLIFT",
      "ticker": "MLIFT",
      "weight": 0.01331,
      "shares_held": 470000,
      "exchange": "-",
      "price": 100
    },
    {
      "name": "CEVA INC",
      "ticker": "CEVA",
      "weight": 0.01036,
      "shares_held": 12669,
      "exchange": "NASDAQ",
      "price": 28.87
    },
    {
      "name": "CHANG WAH TECHNOLOGY LTD",
      "ticker": "6548",
      "weight": 0.01474,
      "shares_held": 300500,
      "exchange": "Gretai Securities Market",
      "price": 1.73
    },
    {
      "name": "CHF CASH",
      "ticker": "CHF",
      "weight": 0.00169,
      "shares_held": 46933,
      "exchange": "-",
      "price": 127.19
    },
    {
      "name": "CHF/USD",
      "ticker": "CHF",
      "weight": 0,
      "shares_held": 4294,
      "exchange": "-",
      "price": 1
    },
    {
      "name": "CHF/USD",
      "ticker": "CHF",
      "weight": 0,
      "shares_held": 4294,
      "exchange": "-",
      "price": 1
    },
    {
      "name": "CHF/USD",
      "ticker": "CHF",
      "weight": 0,
      "shares_held": 4310,
      "exchange": "-",
      "price": 1
    },
    {
      "name": "CHINA RESOURCES MICROELECTRONICS L",
      "ticker": "688396",
      "weight": 0.00674,
      "shares_held": 29698,
      "exchange": "Shanghai Stock Exchange",
      "price": 8.01
    },
    {
      "name": "CHIPBOND TECHNOLOGY CORP",
      "ticker": "6147",
      "weight": 0.03732,
      "shares_held": 286000,
      "exchange": "Gretai Securities Market",
      "price": 4.61
    },
    {
      "name": "CHIPMOS TECHNOLOGIES INC",
      "ticker": "8150",
      "weight": 0.01671,
      "shares_held": 266000,
      "exchange": "Taiwan Stock Exchange",
      "price": 2.22
    },
    {
      "name": "CIRRUS LOGIC INC",
      "ticker": "CRUS",
      "weight": 0.11336,
      "shares_held": 22979,
      "exchange": "NASDAQ",
      "price": 174.17
    },
    {
      "name": "CNH CASH",
      "ticker": "CNH",
      "weight": -0.00487,
      "shares_held": -1176077,
      "exchange": "-",
      "price": 14.63
    },
    {
      "name": "CNH/USD",
      "ticker": "CNH",
      "weight": 0,
      "shares_held": 758511,
      "exchange": "-",
      "price": 1
    },
    {
      "name": "CNH/USD",
      "ticker": "CNH",
      "weight": 0,
      "shares_held": 752669,
      "exchange": "-",
      "price": 1
    },
    {
      "name": "CNH/USD",
      "ticker": "CNH",
      "weight": 0,
      "shares_held": 752669,
      "exchange": "-",
      "price": 1
    },
    {
      "name": "COHU INC",
      "ticker": "COHU",
      "weight": 0.02958,
      "shares_held": 22254,
      "exchange": "NASDAQ",
      "price": 46.93
    },
    {
      "name": "CREDO TECHNOLOGY GROUP HOLDING LTD",
      "ticker": "CRDO",
      "weight": 0.43003,
      "shares_held": 77843,
      "exchange": "NASDAQ",
      "price": 195.04
    },
    {
      "name": "CSI SOLAR LTD A",
      "ticker": "688472",
      "weight": 0.00573,
      "shares_held": 105703,
      "exchange": "Shanghai Stock Exchange",
      "price": 1.91
    },
    {
      "name": "DAQO NEW ENERGY ADR REPRESENTING",
      "ticker": "DQ",
      "weight": 0.01522,
      "shares_held": 23370,
      "exchange": "New York Stock Exchange Inc.",
      "price": 22.99
    },
    {
      "name": "DB HITEK LTD",
      "ticker": "000990",
      "weight": 0.05079,
      "shares_held": 17511,
      "exchange": "Korea Exchange (Stock Market)",
      "price": 102.41
    },
    {
      "name": "DIODES INC",
      "ticker": "DIOD",
      "weight": 0.0737,
      "shares_held": 24923,
      "exchange": "NASDAQ",
      "price": 104.4
    },
    {
      "name": "DISCO CORP",
      "ticker": "6146",
      "weight": 0.56913,
      "shares_held": 44700,
      "exchange": "Tokyo Stock Exchange",
      "price": 449.52
    },
    {
      "name": "DUK SAN NEOLUX LTD",
      "ticker": "213420",
      "weight": 0.00553,
      "shares_held": 5461,
      "exchange": "Korea Exchange (Kosdaq)",
      "price": 35.78
    },
    {
      "name": "ELAN MICROELECTRONICS CORP",
      "ticker": "2458",
      "weight": 0.01855,
      "shares_held": 151000,
      "exchange": "Taiwan Stock Exchange",
      "price": 4.34
    },
    {
      "name": "ELITE ADVANCED LASER CORP",
      "ticker": "3450",
      "weight": 0.02433,
      "shares_held": 85000,
      "exchange": "Taiwan Stock Exchange",
      "price": 10.1
    },
    {
      "name": "ELITE SEMICONDUCTOR MICROELECTRONI",
      "ticker": "3006",
      "weight": 0.01613,
      "shares_held": 116000,
      "exchange": "Taiwan Stock Exchange",
      "price": 4.91
    },
    {
      "name": "ELMOS SEMICONDUCTOR",
      "ticker": "ELG",
      "weight": 0.01875,
      "shares_held": 3217,
      "exchange": "Xetra",
      "price": 205.79
    },
    {
      "name": "EMEMORY TECHNOLOGY INC",
      "ticker": "3529",
      "weight": 0.11056,
      "shares_held": 31500,
      "exchange": "Gretai Securities Market",
      "price": 123.92
    },
    {
      "name": "EMINI TECHNOLOGY SELECT SECTOR JUN",
      "ticker": "IXTM6",
      "weight": 0,
      "shares_held": 10,
      "exchange": "Chicago Mercantile Exchange",
      "price": 3245.2
    },
    {
      "name": "ENNOSTAR INC",
      "ticker": "3714",
      "weight": 0.0157,
      "shares_held": 262000,
      "exchange": "Taiwan Stock Exchange",
      "price": 2.12
    },
    {
      "name": "ENPHASE ENERGY INC",
      "ticker": "ENPH",
      "weight": 0.06565,
      "shares_held": 64795,
      "exchange": "NASDAQ",
      "price": 35.77
    },
    {
      "name": "ENTEGRIS INC",
      "ticker": "ENTG",
      "weight": 0.3292,
      "shares_held": 74513,
      "exchange": "NASDAQ",
      "price": 155.98
    },
    {
      "name": "EO TECHNICS LTD",
      "ticker": "039030",
      "weight": 0.0482,
      "shares_held": 4992,
      "exchange": "Korea Exchange (Kosdaq)",
      "price": 340.91
    },
    {
      "name": "EUGENE TECHNOLOGY LTD",
      "ticker": "084370",
      "weight": 0.0157,
      "shares_held": 6073,
      "exchange": "Korea Exchange (Kosdaq)",
      "price": 91.29
    },
    {
      "name": "EUR CASH",
      "ticker": "EUR",
      "weight": -0.1735,
      "shares_held": -5232737,
      "exchange": "-",
      "price": 117.06
    },
    {
      "name": "EUR/USD",
      "ticker": "EUR",
      "weight": 0,
      "shares_held": 1907676,
      "exchange": "-",
      "price": 1
    },
    {
      "name": "EUR/USD",
      "ticker": "EUR",
      "weight": -0.00003,
      "shares_held": 1872042,
      "exchange": "-",
      "price": 1
    },
    {
      "name": "EUR/USD",
      "ticker": "EUR",
      "weight": 0,
      "shares_held": 1907676,
      "exchange": "-",
      "price": 1
    },
    {
      "name": "EVERLIGHT ELECTRONICS LTD",
      "ticker": "2393",
      "weight": 0.00938,
      "shares_held": 147000,
      "exchange": "Taiwan Stock Exchange",
      "price": 2.25
    },
    {
      "name": "FARADAY TECHNOLOGY CORP",
      "ticker": "3035",
      "weight": 0.0196,
      "shares_held": 117743,
      "exchange": "Taiwan Stock Exchange",
      "price": 5.88
    },
    {
      "name": "FERROTEC CORP",
      "ticker": "6890",
      "weight": 0.02471,
      "shares_held": 18600,
      "exchange": "Tokyo Stock Exchange",
      "price": 46.9
    },
    {
      "name": "FIRST SOLAR INC",
      "ticker": "FSLR",
      "weight": 0.27494,
      "shares_held": 50097,
      "exchange": "NASDAQ",
      "price": 193.76
    },
    {
      "name": "FITIPOWER INTEGRATED TECHNOLOGY IN",
      "ticker": "4961",
      "weight": 0.00446,
      "shares_held": 31000,
      "exchange": "Taiwan Stock Exchange",
      "price": 5.08
    },
    {
      "name": "FORMFACTOR INC",
      "ticker": "FORM",
      "weight": 0.16982,
      "shares_held": 38660,
      "exchange": "NASDAQ",
      "price": 155.08
    },
    {
      "name": "FORMOSA SUMCO TECHNOLOGY CORP",
      "ticker": "3532",
      "weight": 0.00497,
      "shares_held": 32000,
      "exchange": "Taiwan Stock Exchange",
      "price": 5.48
    },
    {
      "name": "FOXSEMICON INTEGRATED TECHNOLOGY I",
      "ticker": "3413",
      "weight": 0.00816,
      "shares_held": 28000,
      "exchange": "Taiwan Stock Exchange",
      "price": 10.3
    },
    {
      "name": "GALAXYCORE INC A",
      "ticker": "688728",
      "weight": 0.00293,
      "shares_held": 53129,
      "exchange": "Shanghai Stock Exchange",
      "price": 1.95
    },
    {
      "name": "GBP CASH",
      "ticker": "GBP",
      "weight": 0.0032,
      "shares_held": 83692,
      "exchange": "-",
      "price": 135.01
    },
    {
      "name": "GCL TECHNOLOGY HOLDINGS LTD",
      "ticker": "3800",
      "weight": 0.04384,
      "shares_held": 12126000,
      "exchange": "Hong Kong Exchanges And Clearing Ltd",
      "price": 0.13
    },
    {
      "name": "GIGADEVICE SEMICONDUCTOR INC A",
      "ticker": "603986",
      "weight": 0.02295,
      "shares_held": 18600,
      "exchange": "Shanghai Stock Exchange",
      "price": 43.56
    },
    {
      "name": "GLOBAL MIXED-MODE TECHNOLOGY INC",
      "ticker": "8081",
      "weight": 0.00469,
      "shares_held": 20000,
      "exchange": "Taiwan Stock Exchange",
      "price": 8.28
    },
    {
      "name": "GLOBAL UNICHIP CORP",
      "ticker": "3443",
      "weight": 0.15252,
      "shares_held": 42000,
      "exchange": "Taiwan Stock Exchange",
      "price": 128.21
    },
    {
      "name": "GLOBALWAFERS LTD",
      "ticker": "6488",
      "weight": 0.07228,
      "shares_held": 138000,
      "exchange": "Gretai Securities Market",
      "price": 18.49
    },
    {
      "name": "GRAND PLASTIC TECHNOLOGY CORP",
      "ticker": "3131",
      "weight": 0.01972,
      "shares_held": 7000,
      "exchange": "Gretai Securities Market",
      "price": 99.46
    },
    {
      "name": "GREATECH TECHNOLOGY",
      "ticker": "GREATEC",
      "weight": 0.00437,
      "shares_held": 242600,
      "exchange": "Bursa Malaysia",
      "price": 0.64
    },
    {
      "name": "GREATEK ELECTRONICS INC",
      "ticker": "2441",
      "weight": 0.01121,
      "shares_held": 141000,
      "exchange": "Taiwan Stock Exchange",
      "price": 2.81
    },
    {
      "name": "GUDENG PRECISION INDUSTRIAL LTD",
      "ticker": "3680",
      "weight": 0.0097,
      "shares_held": 23491,
      "exchange": "Gretai Securities Market",
      "price": 14.58
    },
    {
      "name": "HANA MICRON INC",
      "ticker": "067310",
      "weight": 0.01678,
      "shares_held": 21821,
      "exchange": "Korea Exchange (Kosdaq)",
      "price": 27.15
    },
    {
      "name": "HANGZHOU CHANG CHUAN TECHNOLOGY LT",
      "ticker": "300604",
      "weight": 0.011,
      "shares_held": 16800,
      "exchange": "Shenzhen Stock Exchange",
      "price": 23.12
    },
    {
      "name": "HANGZHOU FIRST APPLIED MATERIAL LT",
      "ticker": "603806",
      "weight": 0.00338,
      "shares_held": 45951,
      "exchange": "Shanghai Stock Exchange",
      "price": 2.6
    },
    {
      "name": "HANGZHOU SILAN MICROELECTRONICS LT",
      "ticker": "600460",
      "weight": 0.00664,
      "shares_held": 57600,
      "exchange": "Shanghai Stock Exchange",
      "price": 4.07
    },
    {
      "name": "HANMI SEMICONDUCTOR LTD",
      "ticker": "042700",
      "weight": 0.12285,
      "shares_held": 21785,
      "exchange": "Korea Exchange (Stock Market)",
      "price": 199.09
    },
    {
      "name": "HKD CASH",
      "ticker": "HKD",
      "weight": -0.00407,
      "shares_held": -1125625,
      "exchange": "-",
      "price": 12.76
    },
    {
      "name": "HKD/USD",
      "ticker": "HKD",
      "weight": 0,
      "shares_held": 608576,
      "exchange": "-",
      "price": 1
    },
    {
      "name": "HKD/USD",
      "ticker": "HKD",
      "weight": 0,
      "shares_held": 608576,
      "exchange": "-",
      "price": 1
    },
    {
      "name": "HKD/USD",
      "ticker": "HKD",
      "weight": 0,
      "shares_held": 655723,
      "exchange": "-",
      "price": 1
    },
    {
      "name": "HPSP LTD",
      "ticker": "403870",
      "weight": 0.03277,
      "shares_held": 32155,
      "exchange": "Korea Exchange (Kosdaq)",
      "price": 35.98
    },
    {
      "name": "HUA HONG SEMICONDUCTOR LTD",
      "ticker": "1347",
      "weight": 0.14461,
      "shares_held": 370000,
      "exchange": "Hong Kong Exchanges And Clearing Ltd",
      "price": 13.8
    },
    {
      "name": "HUA HONG SEMICONDUCTOR LTD A",
      "ticker": "688347",
      "weight": 0.0048,
      "shares_held": 8347,
      "exchange": "Shanghai Stock Exchange",
      "price": 20.31
    },
    {
      "name": "HWATSING TECHNOLOGY LTD A",
      "ticker": "688120",
      "weight": 0.00911,
      "shares_held": 11981,
      "exchange": "Shanghai Stock Exchange",
      "price": 26.84
    },
    {
      "name": "HYGON INFORMATION TECHNOLOGY LTD A",
      "ticker": "688041",
      "weight": 0.07769,
      "shares_held": 65775,
      "exchange": "Shanghai Stock Exchange",
      "price": 41.7
    },
    {
      "name": "ICHOR HOLDINGS LTD",
      "ticker": "ICHR",
      "weight": 0.03554,
      "shares_held": 17689,
      "exchange": "NASDAQ",
      "price": 70.93
    },
    {
      "name": "ILS CASH",
      "ticker": "ILS",
      "weight": -0.01099,
      "shares_held": -1158766,
      "exchange": "-",
      "price": 33.49
    },
    {
      "name": "ILS/USD",
      "ticker": "ILS",
      "weight": 0,
      "shares_held": 527163,
      "exchange": "-",
      "price": 1
    },
    {
      "name": "ILS/USD",
      "ticker": "ILS",
      "weight": 0,
      "shares_held": 527163,
      "exchange": "-",
      "price": 1
    },
    {
      "name": "ILS/USD",
      "ticker": "ILS",
      "weight": 0,
      "shares_held": 527163,
      "exchange": "-",
      "price": 1
    },
    {
      "name": "IMPINJ INC",
      "ticker": "PI",
      "weight": 0.04752,
      "shares_held": 13539,
      "exchange": "NASDAQ",
      "price": 123.91
    },
    {
      "name": "INARI AMERTRON",
      "ticker": "INARI",
      "weight": 0.01641,
      "shares_held": 1261800,
      "exchange": "Bursa Malaysia",
      "price": 0.46
    },
    {
      "name": "INDIE SEMICONDUCTOR INC CLASS A",
      "ticker": "INDI",
      "weight": 0.00994,
      "shares_held": 95892,
      "exchange": "NASDAQ",
      "price": 3.66
    },
    {
      "name": "INFINEON TECHNOLOGIES AG",
      "ticker": "IFX",
      "weight": 1.14565,
      "shares_held": 638096,
      "exchange": "Xetra",
      "price": 63.39
    },
    {
      "name": "INGENIC SEMICONDUCTOR LTD A",
      "ticker": "300223",
      "weight": 0.00695,
      "shares_held": 14000,
      "exchange": "Shenzhen Stock Exchange",
      "price": 17.53
    },
    {
      "name": "INR CASH",
      "ticker": "INR",
      "weight": -0.00068,
      "shares_held": -2263548,
      "exchange": "-",
      "price": 1.06
    },
    {
      "name": "INR/USD",
      "ticker": "INR",
      "weight": 0,
      "shares_held": 1042717,
      "exchange": "-",
      "price": 1
    },
    {
      "name": "INR/USD",
      "ticker": "INR",
      "weight": 0,
      "shares_held": 89072,
      "exchange": "-",
      "price": 1
    },
    {
      "name": "INR/USD",
      "ticker": "INR",
      "weight": 0,
      "shares_held": 1042687,
      "exchange": "-",
      "price": 1
    },
    {
      "name": "INR/USD",
      "ticker": "INR",
      "weight": 0,
      "shares_held": 89072,
      "exchange": "-",
      "price": 1
    },
    {
      "name": "INTEGRATED TECHNOLOGY EXPRESS INC",
      "ticker": "3014",
      "weight": 0.01062,
      "shares_held": 94000,
      "exchange": "Taiwan Stock Exchange",
      "price": 3.99
    },
    {
      "name": "INTEL CORPORATION CORP",
      "ticker": "INTC",
      "weight": 5.06893,
      "shares_held": 2168165,
      "exchange": "NASDAQ",
      "price": 82.54
    },
    {
      "name": "ISC TECHNOLOGY LTD",
      "ticker": "095340",
      "weight": 0.02353,
      "shares_held": 5247,
      "exchange": "Korea Exchange (Kosdaq)",
      "price": 158.33
    },
    {
      "name": "ITH CORP",
      "ticker": "6962",
      "weight": 0.0049,
      "shares_held": 138000,
      "exchange": "Taiwan Stock Exchange",
      "price": 1.25
    },
    {
      "name": "JA SOLAR TECHNOLOGY LTD A",
      "ticker": "002459",
      "weight": 0.00382,
      "shares_held": 84768,
      "exchange": "Shenzhen Stock Exchange",
      "price": 1.59
    },
    {
      "name": "JAPAN MATERIAL LTD",
      "ticker": "6055",
      "weight": 0.00905,
      "shares_held": 28100,
      "exchange": "Tokyo Stock Exchange",
      "price": 11.37
    },
    {
      "name": "JCET GROUP LTD A",
      "ticker": "600584",
      "weight": 0.01135,
      "shares_held": 61000,
      "exchange": "Shanghai Stock Exchange",
      "price": 6.57
    },
    {
      "name": "JENTECH PRECISION INDUSTRIAL LTD",
      "ticker": "3653",
      "weight": 0.20637,
      "shares_held": 42700,
      "exchange": "Taiwan Stock Exchange",
      "price": 170.63
    },
    {
      "name": "JINKO SOLAR LTD A",
      "ticker": "688223",
      "weight": 0.00907,
      "shares_held": 331934,
      "exchange": "Shanghai Stock Exchange",
      "price": 0.96
    },
    {
      "name": "JINKOSOLAR HOLDING ADR REP LTD",
      "ticker": "JKS",
      "weight": 0.00948,
      "shares_held": 14821,
      "exchange": "New York Stock Exchange Inc.",
      "price": 22.59
    },
    {
      "name": "JPY CASH",
      "ticker": "JPY",
      "weight": -0.11441,
      "shares_held": -644292938,
      "exchange": "-",
      "price": 0.63
    },
    {
      "name": "JPY/USD",
      "ticker": "JPY",
      "weight": 0,
      "shares_held": 252709000,
      "exchange": "-",
      "price": 1
    },
    {
      "name": "JPY/USD",
      "ticker": "JPY",
      "weight": -0.00004,
      "shares_held": 252448200,
      "exchange": "-",
      "price": 1
    },
    {
      "name": "JPY/USD",
      "ticker": "JPY",
      "weight": 0,
      "shares_held": 252709000,
      "exchange": "-",
      "price": 1
    },
    {
      "name": "JUSUNG ENGINEERING LTD",
      "ticker": "036930",
      "weight": 0.03915,
      "shares_held": 16558,
      "exchange": "Korea Exchange (Kosdaq)",
      "price": 83.48
    },
    {
      "name": "KING YUAN ELECTRONICS LTD",
      "ticker": "2449",
      "weight": 0.1408,
      "shares_held": 547000,
      "exchange": "Taiwan Stock Exchange",
      "price": 9.09
    },
    {
      "name": "KINSUS INTERCONNECT TECHNOLOGY COR",
      "ticker": "3189",
      "weight": 0.07058,
      "shares_held": 149098,
      "exchange": "Taiwan Stock Exchange",
      "price": 16.71
    },
    {
      "name": "KIOXIA HOLDINGS CORP",
      "ticker": "285A",
      "weight": 0.57046,
      "shares_held": 92900,
      "exchange": "Tokyo Stock Exchange",
      "price": 216.8
    },
    {
      "name": "KLA CORP",
      "ticker": "KLAC",
      "weight": 3.50374,
      "shares_held": 63928,
      "exchange": "NASDAQ",
      "price": 1935
    },
    {
      "name": "KOH YOUNG TECHNOLOGY INC",
      "ticker": "098460",
      "weight": 0.02465,
      "shares_held": 30541,
      "exchange": "Korea Exchange (Kosdaq)",
      "price": 28.5
    },
    {
      "name": "KOKUSAI ELECTRIC CORP",
      "ticker": "6525",
      "weight": 0.11318,
      "shares_held": 95900,
      "exchange": "Tokyo Stock Exchange",
      "price": 41.67
    },
    {
      "name": "KRW CASH",
      "ticker": "KRW",
      "weight": -0.11444,
      "shares_held": -5996870086,
      "exchange": "-",
      "price": 0.07
    },
    {
      "name": "KRW/USD",
      "ticker": "KRW",
      "weight": 0,
      "shares_held": 2010961000,
      "exchange": "-",
      "price": 1
    },
    {
      "name": "KRW/USD",
      "ticker": "KRW",
      "weight": 0,
      "shares_held": 2010961000,
      "exchange": "-",
      "price": 1
    },
    {
      "name": "KRW/USD",
      "ticker": "KRW",
      "weight": -0.00009,
      "shares_held": 2021956850,
      "exchange": "-",
      "price": 1
    },
    {
      "name": "KRW/USD",
      "ticker": "KRW",
      "weight": 0,
      "shares_held": 683382669,
      "exchange": "-",
      "price": 1
    },
    {
      "name": "KULICKE AND SOFFA INDUSTRIES INC",
      "ticker": "KLIC",
      "weight": 0.05625,
      "shares_held": 22643,
      "exchange": "NASDAQ",
      "price": 87.71
    },
    {
      "name": "LAM RESEARCH CORP",
      "ticker": "LRCX",
      "weight": 4.07413,
      "shares_held": 537152,
      "exchange": "NASDAQ",
      "price": 267.78
    },
    {
      "name": "LAND MARK CORP",
      "ticker": "3081",
      "weight": 0.08375,
      "shares_held": 33000,
      "exchange": "Gretai Securities Market",
      "price": 89.6
    },
    {
      "name": "LASERTEC CORP",
      "ticker": "6920",
      "weight": 0.31526,
      "shares_held": 39400,
      "exchange": "Tokyo Stock Exchange",
      "price": 282.5
    },
    {
      "name": "LATTICE SEMICONDUCTOR CORP",
      "ticker": "LSCC",
      "weight": 0.2352,
      "shares_held": 67622,
      "exchange": "NASDAQ",
      "price": 122.8
    },
    {
      "name": "LEENO INDUSTRIAL INC",
      "ticker": "058470",
      "weight": 0.06008,
      "shares_held": 25308,
      "exchange": "Korea Exchange (Kosdaq)",
      "price": 83.81
    },
    {
      "name": "LONGI GREEN ENERGY TECHNOLOGY LTD",
      "ticker": "601012",
      "weight": 0.01918,
      "shares_held": 266140,
      "exchange": "Shanghai Stock Exchange",
      "price": 2.54
    },
    {
      "name": "LOONGSON TECHNOLOGY CORP LTD A",
      "ticker": "688047",
      "weight": 0.00425,
      "shares_held": 6672,
      "exchange": "Shanghai Stock Exchange",
      "price": 22.51
    },
    {
      "name": "LX SEMICON LTD",
      "ticker": "108320",
      "weight": 0.00715,
      "shares_held": 5775,
      "exchange": "Korea Exchange (Stock Market)",
      "price": 43.73
    },
    {
      "name": "M31 TECHNOLOGY CORPORATION CORP",
      "ticker": "6643",
      "weight": 0.00432,
      "shares_held": 8400,
      "exchange": "Gretai Securities Market",
      "price": 18.14
    },
    {
      "name": "MACHVISION INC",
      "ticker": "3563",
      "weight": 0.0126,
      "shares_held": 15400,
      "exchange": "Taiwan Stock Exchange",
      "price": 28.88
    },
    {
      "name": "MACOM TECHNOLOGY SOLUTIONS INC",
      "ticker": "MTSI",
      "weight": 0.26882,
      "shares_held": 32995,
      "exchange": "NASDAQ",
      "price": 287.64
    },
    {
      "name": "MACRONIX INTERNATIONAL LTD",
      "ticker": "2337",
      "weight": 0.1112,
      "shares_held": 936000,
      "exchange": "Taiwan Stock Exchange",
      "price": 4.19
    },
    {
      "name": "MALAYSIAN PACIFIC INDUSTRIES",
      "ticker": "MPI",
      "weight": 0.01187,
      "shares_held": 43900,
      "exchange": "Bursa Malaysia",
      "price": 9.54
    },
    {
      "name": "MARKETECH INTERNATIONAL CORP",
      "ticker": "6196",
      "weight": 0.01355,
      "shares_held": 39000,
      "exchange": "Taiwan Stock Exchange",
      "price": 12.27
    },
    {
      "name": "MARVELL TECHNOLOGY INC",
      "ticker": "MRVL",
      "weight": 1.91896,
      "shares_held": 412328,
      "exchange": "NASDAQ",
      "price": 164.31
    },
    {
      "name": "MAXLINEAR INC",
      "ticker": "MXL",
      "weight": 0.06878,
      "shares_held": 40258,
      "exchange": "NASDAQ",
      "price": 60.32
    },
    {
      "name": "MEDIATEK INC",
      "ticker": "2454",
      "weight": 1.6239,
      "shares_held": 741000,
      "exchange": "Taiwan Stock Exchange",
      "price": 77.37
    },
    {
      "name": "MEGACHIPS CORP",
      "ticker": "6875",
      "weight": 0.00678,
      "shares_held": 3700,
      "exchange": "Tokyo Stock Exchange",
      "price": 64.7
    },
    {
      "name": "MELEXIS NV",
      "ticker": "MELE",
      "weight": 0.02465,
      "shares_held": 10589,
      "exchange": "Nyse Euronext - Euronext Brussels",
      "price": 82.18
    },
    {
      "name": "MICROCHIP TECHNOLOGY INC",
      "ticker": "MCHP",
      "weight": 0.66754,
      "shares_held": 263505,
      "exchange": "NASDAQ",
      "price": 89.44
    },
    {
      "name": "MICRON TECHNOLOGY INC",
      "ticker": "MU",
      "weight": 7.44703,
      "shares_held": 529312,
      "exchange": "NASDAQ",
      "price": 496.72
    },
    {
      "name": "MICRONICS JAPAN LTD",
      "ticker": "6871",
      "weight": 0.03318,
      "shares_held": 14900,
      "exchange": "Tokyo Stock Exchange",
      "price": 78.62
    },
    {
      "name": "MITSUI HIGH TEC INC",
      "ticker": "6966",
      "weight": 0.00631,
      "shares_held": 53400,
      "exchange": "Tokyo Stock Exchange",
      "price": 4.17
    },
    {
      "name": "MKS",
      "ticker": "MKSI",
      "weight": 0.2632,
      "shares_held": 33071,
      "exchange": "NASDAQ",
      "price": 280.98
    },
    {
      "name": "MONOLITHIC POWER SYSTEMS INC",
      "ticker": "MPWR",
      "weight": 1.07843,
      "shares_held": 23329,
      "exchange": "NASDAQ",
      "price": 1632.06
    },
    {
      "name": "MONTAGE TECHNOLOGY LTD A",
      "ticker": "688008",
      "weight": 0.02069,
      "shares_held": 30536,
      "exchange": "Shanghai Stock Exchange",
      "price": 23.92
    },
    {
      "name": "MPI CORP",
      "ticker": "6223",
      "weight": 0.17158,
      "shares_held": 41000,
      "exchange": "Gretai Securities Market",
      "price": 147.75
    },
    {
      "name": "MSCI TAIWAN INDEX MAY 26",
      "ticker": "HJAK6",
      "weight": 0,
      "shares_held": 7,
      "exchange": "Hong Kong Futures Exchange Ltd.",
      "price": 1774.5
    },
    {
      "name": "MYR CASH",
      "ticker": "MYR",
      "weight": 0.00074,
      "shares_held": 103686,
      "exchange": "-",
      "price": 25.22
    },
    {
      "name": "MYR/USD",
      "ticker": "MYR",
      "weight": 0,
      "shares_held": 51612,
      "exchange": "-",
      "price": 1
    },
    {
      "name": "MYR/USD",
      "ticker": "MYR",
      "weight": 0,
      "shares_held": 51612,
      "exchange": "-",
      "price": 1
    },
    {
      "name": "MYR/USD",
      "ticker": "MYR",
      "weight": 0,
      "shares_held": 51164,
      "exchange": "-",
      "price": 1
    },
    {
      "name": "NANYA TECHNOLOGY CORP",
      "ticker": "2408",
      "weight": 0.10902,
      "shares_held": 588000,
      "exchange": "Taiwan Stock Exchange",
      "price": 6.55
    },
    {
      "name": "NATIONAL SILICON INDUSTRY GROUP LT",
      "ticker": "688126",
      "weight": 0.00518,
      "shares_held": 60146,
      "exchange": "Shanghai Stock Exchange",
      "price": 3.04
    },
    {
      "name": "NAURA TECHNOLOGY GROUP LTD A",
      "ticker": "002371",
      "weight": 0.04604,
      "shares_held": 23505,
      "exchange": "Shenzhen Stock Exchange",
      "price": 69.16
    },
    {
      "name": "NAVITAS SEMICONDUCTOR CORP",
      "ticker": "NVTS",
      "weight": 0.04797,
      "shares_held": 98010,
      "exchange": "NASDAQ",
      "price": 17.28
    },
    {
      "name": "NEXCHIP SEMICONDUCTOR CORP A",
      "ticker": "688249",
      "weight": 0.00722,
      "shares_held": 58747,
      "exchange": "Shanghai Stock Exchange",
      "price": 4.34
    },
    {
      "name": "NOK CASH",
      "ticker": "NOK",
      "weight": 0.00233,
      "shares_held": 769868,
      "exchange": "-",
      "price": 10.7
    },
    {
      "name": "NOK/USD",
      "ticker": "NOK",
      "weight": 0,
      "shares_held": 117559,
      "exchange": "-",
      "price": 1
    },
    {
      "name": "NOK/USD",
      "ticker": "NOK",
      "weight": 0,
      "shares_held": 117559,
      "exchange": "-",
      "price": 1
    },
    {
      "name": "NOK/USD",
      "ticker": "NOK",
      "weight": 0,
      "shares_held": 118200,
      "exchange": "-",
      "price": 1
    },
    {
      "name": "NORDIC SEMICONDUCTOR",
      "ticker": "NOD",
      "weight": 0.05113,
      "shares_held": 89610,
      "exchange": "Oslo Bors Asa",
      "price": 20.15
    },
    {
      "name": "NOVA LTD",
      "ticker": "NVMI",
      "weight": 0.21548,
      "shares_held": 14556,
      "exchange": "Tel Aviv Stock Exchange",
      "price": 522.65
    },
    {
      "name": "NOVATEK MICROELECTRONICS CORP",
      "ticker": "3034",
      "weight": 0.10722,
      "shares_held": 285000,
      "exchange": "Taiwan Stock Exchange",
      "price": 13.28
    },
    {
      "name": "NUVOTON TECHNOLOGY CORP",
      "ticker": "4919",
      "weight": 0.01488,
      "shares_held": 114000,
      "exchange": "Taiwan Stock Exchange",
      "price": 4.61
    },
    {
      "name": "NVIDIA CORP",
      "ticker": "NVDA",
      "weight": 6.75014,
      "shares_held": 1144265,
      "exchange": "NASDAQ",
      "price": 208.27
    },
    {
      "name": "NXP SEMICONDUCTORS NV",
      "ticker": "NXPI",
      "weight": 0.8445,
      "shares_held": 122174,
      "exchange": "NASDAQ",
      "price": 244.04
    },
    {
      "name": "OMNIVISION INTEGRATED CIRCUITS GRO",
      "ticker": "603501",
      "weight": 0.01567,
      "shares_held": 39765,
      "exchange": "Shanghai Stock Exchange",
      "price": 13.92
    },
    {
      "name": "ON SEMICONDUCTOR CORP",
      "ticker": "ON",
      "weight": 0.54757,
      "shares_held": 196465,
      "exchange": "NASDAQ",
      "price": 98.4
    },
    {
      "name": "ONTO INNOVATION INC",
      "ticker": "ONTO",
      "weight": 0.21229,
      "shares_held": 24345,
      "exchange": "New York Stock Exchange Inc.",
      "price": 307.86
    },
    {
      "name": "ORIENT SEMICONDUCTOR ELECTRONICS L",
      "ticker": "2329",
      "weight": 0.01503,
      "shares_held": 302000,
      "exchange": "Taiwan Stock Exchange",
      "price": 1.76
    },
    {
      "name": "PAN JIT INTERNATIONAL INC",
      "ticker": "2481",
      "weight": 0.0126,
      "shares_held": 140000,
      "exchange": "Taiwan Stock Exchange",
      "price": 3.18
    },
    {
      "name": "PARADE TECHNOLOGIES LTD",
      "ticker": "4966",
      "weight": 0.01482,
      "shares_held": 25377,
      "exchange": "Gretai Securities Market",
      "price": 20.62
    },
    {
      "name": "PDF SOLUTIONS INC",
      "ticker": "PDFS",
      "weight": 0.01747,
      "shares_held": 13267,
      "exchange": "NASDAQ",
      "price": 46.49
    },
    {
      "name": "PENGUIN SOLUTIONS INC",
      "ticker": "PENG",
      "weight": 0.02371,
      "shares_held": 27281,
      "exchange": "NASDAQ",
      "price": 30.69
    },
    {
      "name": "PHISON ELECTRONICS CORP",
      "ticker": "8299",
      "weight": 0.1391,
      "shares_held": 92000,
      "exchange": "Gretai Securities Market",
      "price": 53.38
    },
    {
      "name": "PHOENIX SILICON INTERNATIONAL CORP",
      "ticker": "8028",
      "weight": 0.02722,
      "shares_held": 125000,
      "exchange": "Taiwan Stock Exchange",
      "price": 7.69
    },
    {
      "name": "PHOTRONICS INC",
      "ticker": "PLAB",
      "weight": 0.04078,
      "shares_held": 27544,
      "exchange": "NASDAQ",
      "price": 52.27
    },
    {
      "name": "PIOTECH INC A",
      "ticker": "688072",
      "weight": 0.01068,
      "shares_held": 6703,
      "exchange": "Shanghai Stock Exchange",
      "price": 56.27
    },
    {
      "name": "PIXART IMAGING INC",
      "ticker": "3227",
      "weight": 0.00878,
      "shares_held": 46000,
      "exchange": "Gretai Securities Market",
      "price": 6.74
    },
    {
      "name": "POWER INTEGRATIONS INC",
      "ticker": "POWI",
      "weight": 0.06212,
      "shares_held": 29825,
      "exchange": "NASDAQ",
      "price": 73.54
    },
    {
      "name": "POWERCHIP SEMICONDUCTOR MANUFACTUR",
      "ticker": "6770",
      "weight": 0.07432,
      "shares_held": 1561000,
      "exchange": "Taiwan Stock Exchange",
      "price": 1.68
    },
    {
      "name": "POWERTECH TECHNOLOGY INC",
      "ticker": "6239",
      "weight": 0.0618,
      "shares_held": 327000,
      "exchange": "Taiwan Stock Exchange",
      "price": 6.67
    },
    {
      "name": "PSK HOLDINGS INC",
      "ticker": "031980",
      "weight": 0.01144,
      "shares_held": 5282,
      "exchange": "Korea Exchange (Kosdaq)",
      "price": 76.47
    },
    {
      "name": "QNITY ELECTRONICS INC",
      "ticker": "Q",
      "weight": 0.41973,
      "shares_held": 102567,
      "exchange": "New York Stock Exchange Inc.",
      "price": 144.48
    },
    {
      "name": "QORVO INC",
      "ticker": "QRVO",
      "weight": 0.1094,
      "shares_held": 43991,
      "exchange": "NASDAQ",
      "price": 87.8
    },
    {
      "name": "QUALCOMM INC",
      "ticker": "QCOM",
      "weight": 2.18292,
      "shares_held": 517760,
      "exchange": "NASDAQ",
      "price": 148.85
    },
    {
      "name": "RADIANT OPTO-ELECTRONICS CORP",
      "ticker": "6176",
      "weight": 0.02356,
      "shares_held": 238000,
      "exchange": "Taiwan Stock Exchange",
      "price": 3.5
    },
    {
      "name": "RAMBUS INC",
      "ticker": "RMBS",
      "weight": 0.21675,
      "shares_held": 48310,
      "exchange": "NASDAQ",
      "price": 158.4
    },
    {
      "name": "RAYDIUM SEMI-CONDUCTOR CORP",
      "ticker": "3592",
      "weight": 0.00475,
      "shares_held": 22000,
      "exchange": "Taiwan Stock Exchange",
      "price": 7.63
    },
    {
      "name": "REALTEK SEMICONDUCTOR CORP",
      "ticker": "2379",
      "weight": 0.1203,
      "shares_held": 248000,
      "exchange": "Taiwan Stock Exchange",
      "price": 17.13
    },
    {
      "name": "RENESAS ELECTRONICS CORP",
      "ticker": "6723",
      "weight": 0.48431,
      "shares_held": 868300,
      "exchange": "Tokyo Stock Exchange",
      "price": 19.69
    },
    {
      "name": "RIGETTI COMPUTING INC",
      "ticker": "RGTI",
      "weight": 0.08061,
      "shares_held": 171336,
      "exchange": "NASDAQ",
      "price": 16.61
    },
    {
      "name": "ROCKCHIP ELECTRONICS LTD A",
      "ticker": "603893",
      "weight": 0.00948,
      "shares_held": 12800,
      "exchange": "Shanghai Stock Exchange",
      "price": 26.14
    },
    {
      "name": "ROHM LTD",
      "ticker": "6963",
      "weight": 0.11433,
      "shares_held": 171000,
      "exchange": "Tokyo Stock Exchange",
      "price": 23.6
    },
    {
      "name": "RORZE CORP",
      "ticker": "6323",
      "weight": 0.03004,
      "shares_held": 46500,
      "exchange": "Tokyo Stock Exchange",
      "price": 22.81
    },
    {
      "name": "RS TECHNOLOGIES LTD",
      "ticker": "3445",
      "weight": 0.00231,
      "shares_held": 2600,
      "exchange": "Tokyo Stock Exchange",
      "price": 31.35
    },
    {
      "name": "SANAN OPTOELECTRONICS LTD A",
      "ticker": "600703",
      "weight": 0.01327,
      "shares_held": 212000,
      "exchange": "Shanghai Stock Exchange",
      "price": 2.21
    },
    {
      "name": "SANKEN ELECTRIC LTD",
      "ticker": "6707",
      "weight": 0.0193,
      "shares_held": 11200,
      "exchange": "Tokyo Stock Exchange",
      "price": 60.85
    },
    {
      "name": "SCREEN HOLDINGS LTD",
      "ticker": "7735",
      "weight": 0.14922,
      "shares_held": 79200,
      "exchange": "Tokyo Stock Exchange",
      "price": 66.52
    },
    {
      "name": "SEMTECH CORP",
      "ticker": "SMTC",
      "weight": 0.14436,
      "shares_held": 46423,
      "exchange": "NASDAQ",
      "price": 109.79
    },
    {
      "name": "SG MICRO CORP A",
      "ticker": "300661",
      "weight": 0.00872,
      "shares_held": 23539,
      "exchange": "Shenzhen Stock Exchange",
      "price": 13.07
    },
    {
      "name": "SGD CASH",
      "ticker": "SGD",
      "weight": 0.00131,
      "shares_held": 59043,
      "exchange": "-",
      "price": 78.31
    },
    {
      "name": "SGD/USD",
      "ticker": "SGD",
      "weight": 0,
      "shares_held": 4728,
      "exchange": "-",
      "price": 1
    },
    {
      "name": "SGD/USD",
      "ticker": "SGD",
      "weight": 0,
      "shares_held": 3960,
      "exchange": "-",
      "price": 1
    },
    {
      "name": "SGD/USD",
      "ticker": "SGD",
      "weight": 0,
      "shares_held": 3960,
      "exchange": "-",
      "price": 1
    },
    {
      "name": "SHENZHEN GOODIX TECHNOLOGY LTD A",
      "ticker": "603160",
      "weight": 0.00375,
      "shares_held": 13900,
      "exchange": "Shanghai Stock Exchange",
      "price": 9.52
    },
    {
      "name": "SHIBAURA MECHATRONICS CORP",
      "ticker": "6590",
      "weight": 0.02466,
      "shares_held": 28000,
      "exchange": "Tokyo Stock Exchange",
      "price": 31.1
    },
    {
      "name": "SHUNSIN TECHNOLOGY HOLDINGS LTD",
      "ticker": "6451",
      "weight": 0.00651,
      "shares_held": 18000,
      "exchange": "Taiwan Stock Exchange",
      "price": 12.77
    },
    {
      "name": "SIGURD MICROELECTRONICS CORP",
      "ticker": "6257",
      "weight": 0.03996,
      "shares_held": 240000,
      "exchange": "Taiwan Stock Exchange",
      "price": 5.88
    },
    {
      "name": "SILERGY CORP",
      "ticker": "6415",
      "weight": 0.06175,
      "shares_held": 157360,
      "exchange": "Taiwan Stock Exchange",
      "price": 13.85
    },
    {
      "name": "SILICON INTEGRATED SYSTEM CORP",
      "ticker": "2363",
      "weight": 0.00927,
      "shares_held": 187200,
      "exchange": "Taiwan Stock Exchange",
      "price": 1.75
    },
    {
      "name": "SILICON LABORATORIES INC",
      "ticker": "SLAB",
      "weight": 0.1037,
      "shares_held": 16989,
      "exchange": "NASDAQ",
      "price": 215.5
    },
    {
      "name": "SILTRONIC N AG",
      "ticker": "WAF",
      "weight": 0.01395,
      "shares_held": 5691,
      "exchange": "Xetra",
      "price": 86.57
    },
    {
      "name": "SINO-AMERICAN SILICON PRODUCTS INC",
      "ticker": "5483",
      "weight": 0.03264,
      "shares_held": 279000,
      "exchange": "Gretai Securities Market",
      "price": 4.13
    },
    {
      "name": "SITIME CORP",
      "ticker": "SITM",
      "weight": 0.17624,
      "shares_held": 10911,
      "exchange": "NASDAQ",
      "price": 570.26
    },
    {
      "name": "SITRONIX TECHNOLOGY CORP",
      "ticker": "8016",
      "weight": 0.00929,
      "shares_held": 45000,
      "exchange": "Taiwan Stock Exchange",
      "price": 7.29
    },
    {
      "name": "SK HYNIX INC",
      "ticker": "000660",
      "weight": 4.8637,
      "shares_held": 208566,
      "exchange": "Korea Exchange (Stock Market)",
      "price": 823.31
    },
    {
      "name": "SKYWATER TECHNOLOGY INC",
      "ticker": "SKYT",
      "weight": 0.0139,
      "shares_held": 14617,
      "exchange": "NASDAQ",
      "price": 33.58
    },
    {
      "name": "SKYWORKS SOLUTIONS INC",
      "ticker": "SWKS",
      "weight": 0.11413,
      "shares_held": 63305,
      "exchange": "NASDAQ",
      "price": 63.65
    },
    {
      "name": "SOCIONEXT INC",
      "ticker": "6526",
      "weight": 0.0359,
      "shares_held": 98800,
      "exchange": "Tokyo Stock Exchange",
      "price": 12.83
    },
    {
      "name": "SOITEC SA",
      "ticker": "SOI",
      "weight": 0.0498,
      "shares_held": 13334,
      "exchange": "Nyse Euronext - Euronext Paris",
      "price": 131.87
    },
    {
      "name": "SOLAREDGE TECHNOLOGIES INC",
      "ticker": "SEDG",
      "weight": 0.04207,
      "shares_held": 32407,
      "exchange": "NASDAQ",
      "price": 45.83
    },
    {
      "name": "STMICROELECTRONICS NV",
      "ticker": "STMPA",
      "weight": 0.47757,
      "shares_held": 332109,
      "exchange": "Nyse Euronext - Euronext Paris",
      "price": 50.77
    },
    {
      "name": "STOXX 600 TECH JUN 26",
      "ticker": "ULM6",
      "weight": 0,
      "shares_held": 4,
      "exchange": "Eurex Deutschland",
      "price": 1053.54
    },
    {
      "name": "SUMCO CORP",
      "ticker": "3436",
      "weight": 0.06645,
      "shares_held": 166900,
      "exchange": "Tokyo Stock Exchange",
      "price": 14.06
    },
    {
      "name": "SUSS MICROTEC N",
      "ticker": "SMHN",
      "weight": 0.02005,
      "shares_held": 8649,
      "exchange": "Xetra",
      "price": 81.83
    },
    {
      "name": "SYNAPTICS INC",
      "ticker": "SYNA",
      "weight": 0.05458,
      "shares_held": 20531,
      "exchange": "NASDAQ",
      "price": 93.86
    },
    {
      "name": "TAESUNG COLTD LTD",
      "ticker": "323280",
      "weight": 0.0115,
      "shares_held": 7879,
      "exchange": "Korea Exchange (Kosdaq)",
      "price": 51.54
    },
    {
      "name": "TAIWAN SEMICONDUCTOR MANUFACTURING",
      "ticker": "2330",
      "weight": 6.85718,
      "shares_held": 3487000,
      "exchange": "Taiwan Stock Exchange",
      "price": 69.43
    },
    {
      "name": "TCL ZHONGHUAN RENEWABLE ENERGY TEC",
      "ticker": "002129",
      "weight": 0.00337,
      "shares_held": 94175,
      "exchange": "Shenzhen Stock Exchange",
      "price": 1.26
    },
    {
      "name": "TECHNOPROBE SPA",
      "ticker": "TPRO",
      "weight": 0.03838,
      "shares_held": 64771,
      "exchange": "Borsa Italiana",
      "price": 20.92
    },
    {
      "name": "TECHWING INC",
      "ticker": "089030",
      "weight": 0.01793,
      "shares_held": 15205,
      "exchange": "Korea Exchange (Kosdaq)",
      "price": 41.64
    },
    {
      "name": "TERADYNE INC",
      "ticker": "TER",
      "weight": 0.90373,
      "shares_held": 76317,
      "exchange": "NASDAQ",
      "price": 418.08
    },
    {
      "name": "TEXAS INSTRUMENT INC",
      "ticker": "TXN",
      "weight": 3.47174,
      "shares_held": 442271,
      "exchange": "NASDAQ",
      "price": 277.14
    },
    {
      "name": "TIANSHUI HUATIAN TECHNOLOGY LTD A",
      "ticker": "002185",
      "weight": 0.00796,
      "shares_held": 154300,
      "exchange": "Shenzhen Stock Exchange",
      "price": 1.82
    },
    {
      "name": "TOKAI CARBON KOREA LTD",
      "ticker": "064760",
      "weight": 0.01252,
      "shares_held": 2130,
      "exchange": "Korea Exchange (Kosdaq)",
      "price": 207.51
    },
    {
      "name": "TOKYO ELECTRON LTD",
      "ticker": "8035",
      "weight": 1.76679,
      "shares_held": 217000,
      "exchange": "Tokyo Stock Exchange",
      "price": 287.45
    },
    {
      "name": "TOKYO SEIMITSU LTD",
      "ticker": "7729",
      "weight": 0.05695,
      "shares_held": 18400,
      "exchange": "Tokyo Stock Exchange",
      "price": 109.28
    },
    {
      "name": "TONGFU MICROELECTRONICS LTD A",
      "ticker": "002156",
      "weight": 0.01172,
      "shares_held": 58400,
      "exchange": "Shenzhen Stock Exchange",
      "price": 7.08
    },
    {
      "name": "TONGWEI LTD A",
      "ticker": "600438",
      "weight": 0.00868,
      "shares_held": 117400,
      "exchange": "Shanghai Stock Exchange",
      "price": 2.61
    },
    {
      "name": "TOPCO SCIENTIFIC LTD",
      "ticker": "5434",
      "weight": 0.03705,
      "shares_held": 98953,
      "exchange": "Taiwan Stock Exchange",
      "price": 13.22
    },
    {
      "name": "TOWA CORP",
      "ticker": "6315",
      "weight": 0.01514,
      "shares_held": 32800,
      "exchange": "Tokyo Stock Exchange",
      "price": 16.29
    },
    {
      "name": "TOWER SEMICONDUCTOR LTD",
      "ticker": "TSEM",
      "weight": 0.31803,
      "shares_held": 55055,
      "exchange": "Tel Aviv Stock Exchange",
      "price": 203.94
    },
    {
      "name": "TRI CHEMICAL LABORATORIES INC",
      "ticker": "4369",
      "weight": 0.00682,
      "shares_held": 12000,
      "exchange": "Tokyo Stock Exchange",
      "price": 20.06
    },
    {
      "name": "TRINA SOLAR LTD A",
      "ticker": "688599",
      "weight": 0.00431,
      "shares_held": 64214,
      "exchange": "Shanghai Stock Exchange",
      "price": 2.37
    },
    {
      "name": "TRY CASH",
      "ticker": "TRY",
      "weight": 0.00194,
      "shares_held": 3086535,
      "exchange": "-",
      "price": 2.22
    },
    {
      "name": "TWD CASH",
      "ticker": "TWD",
      "weight": -0.18968,
      "shares_held": -210760587,
      "exchange": "-",
      "price": 3.18
    },
    {
      "name": "TWD/USD",
      "ticker": "TWD",
      "weight": 0,
      "shares_held": 36152219,
      "exchange": "-",
      "price": 1
    },
    {
      "name": "TWD/USD",
      "ticker": "TWD",
      "weight": -0.00001,
      "shares_held": 87330850,
      "exchange": "-",
      "price": 1
    },
    {
      "name": "TWD/USD",
      "ticker": "TWD",
      "weight": -0.00001,
      "shares_held": 87330850,
      "exchange": "-",
      "price": 1
    },
    {
      "name": "ULTRA CLEAN HOLDINGS INC",
      "ticker": "UCTT",
      "weight": 0.05656,
      "shares_held": 24056,
      "exchange": "NASDAQ",
      "price": 83.01
    },
    {
      "name": "ULVAC INC",
      "ticker": "6728",
      "weight": 0.04373,
      "shares_held": 25200,
      "exchange": "Tokyo Stock Exchange",
      "price": 61.27
    },
    {
      "name": "UMS INTEGRATION LTD",
      "ticker": "558",
      "weight": 0.01354,
      "shares_held": 285250,
      "exchange": "Singapore Exchange",
      "price": 1.68
    },
    {
      "name": "UNIGROUP GUOXIN MICROELECTRONICS L",
      "ticker": "002049",
      "weight": 0.00857,
      "shares_held": 29079,
      "exchange": "Shenzhen Stock Exchange",
      "price": 10.4
    },
    {
      "name": "UNISEM M",
      "ticker": "UNISEM",
      "weight": 0.00346,
      "shares_held": 157400,
      "exchange": "Bursa Malaysia",
      "price": 0.78
    },
    {
      "name": "UNITED MICRO ELECTRONICS CORP",
      "ticker": "2303",
      "weight": 0.37333,
      "shares_held": 5568000,
      "exchange": "Taiwan Stock Exchange",
      "price": 2.37
    },
    {
      "name": "UNITED NOVA TECHNOLOGY LTD A",
      "ticker": "688469",
      "weight": 0.00569,
      "shares_held": 205824,
      "exchange": "Shanghai Stock Exchange",
      "price": 0.98
    },
    {
      "name": "UNIVERSAL DISPLAY CORP",
      "ticker": "OLED",
      "weight": 0.06118,
      "shares_held": 21810,
      "exchange": "NASDAQ",
      "price": 99.03
    },
    {
      "name": "UPI SEMICONDUCTOR CORP",
      "ticker": "6719",
      "weight": 0.00408,
      "shares_held": 25000,
      "exchange": "Taiwan Stock Exchange",
      "price": 5.77
    },
    {
      "name": "USD CASH",
      "ticker": "USD",
      "weight": 0.68812,
      "shares_held": 24294321,
      "exchange": "-",
      "price": 100
    },
    {
      "name": "VANGUARD INTERNATIONAL SEMICONDUCT",
      "ticker": "5347",
      "weight": 0.07183,
      "shares_held": 568025,
      "exchange": "Gretai Securities Market",
      "price": 4.46
    },
    {
      "name": "VEECO INSTRUMENTS INC",
      "ticker": "VECO",
      "weight": 0.04505,
      "shares_held": 30744,
      "exchange": "NASDAQ",
      "price": 51.73
    },
    {
      "name": "VERISILICON MICROELECTRONICS (SHAN",
      "ticker": "688521",
      "weight": 0.0179,
      "shares_held": 18882,
      "exchange": "Shanghai Stock Exchange",
      "price": 33.46
    },
    {
      "name": "VIA TECHNOLOGIES INC",
      "ticker": "2388",
      "weight": 0.0095,
      "shares_held": 135000,
      "exchange": "Taiwan Stock Exchange",
      "price": 2.48
    },
    {
      "name": "VISERA TECHNOLOGIES LTD",
      "ticker": "6789",
      "weight": 0.02139,
      "shares_held": 42000,
      "exchange": "Taiwan Stock Exchange",
      "price": 17.98
    },
    {
      "name": "VISUAL PHOTONICS EPITAXY LTD",
      "ticker": "2455",
      "weight": 0.0246,
      "shares_held": 79000,
      "exchange": "Taiwan Stock Exchange",
      "price": 10.99
    },
    {
      "name": "VITROX CORPORATION",
      "ticker": "VITROX",
      "weight": 0.01216,
      "shares_held": 308500,
      "exchange": "Bursa Malaysia",
      "price": 1.39
    },
    {
      "name": "WAAREE ENERGIES LTD",
      "ticker": "WAAREEENER",
      "weight": 0.04412,
      "shares_held": 44409,
      "exchange": "National Stock Exchange Of India",
      "price": 35.07
    },
    {
      "name": "WIN SEMICONDUCTORS CORP",
      "ticker": "3105",
      "weight": 0.07828,
      "shares_held": 159000,
      "exchange": "Gretai Securities Market",
      "price": 17.38
    },
    {
      "name": "WINBOND ELECTRONICS CORP",
      "ticker": "2344",
      "weight": 0.1244,
      "shares_held": 1567102,
      "exchange": "Taiwan Stock Exchange",
      "price": 2.8
    },
    {
      "name": "WINWAY TECHNOLOGY LTD",
      "ticker": "6515",
      "weight": 0.09959,
      "shares_held": 11000,
      "exchange": "Taiwan Stock Exchange",
      "price": 319.65
    },
    {
      "name": "WONIK IPS LTD",
      "ticker": "240810",
      "weight": 0.03132,
      "shares_held": 14138,
      "exchange": "Korea Exchange (Kosdaq)",
      "price": 78.22
    },
    {
      "name": "X-FAB SILICON FOUNDRIES",
      "ticker": "XFAB",
      "weight": 0.00499,
      "shares_held": 22248,
      "exchange": "Nyse Euronext - Euronext Paris",
      "price": 7.92
    },
    {
      "name": "XINJIANG DAQO NEW ENERGY LTD A",
      "ticker": "688303",
      "weight": 0.00486,
      "shares_held": 51202,
      "exchange": "Shanghai Stock Exchange",
      "price": 3.35
    },
    {
      "name": "XINTEC INC",
      "ticker": "3374",
      "weight": 0.01786,
      "shares_held": 100000,
      "exchange": "Gretai Securities Market",
      "price": 6.31
    },
    {
      "name": "XINYI SOLAR HOLDINGS LTD",
      "ticker": "968",
      "weight": 0.02755,
      "shares_held": 2490000,
      "exchange": "Hong Kong Exchanges And Clearing Ltd",
      "price": 0.39
    },
    {
      "name": "YCC CORP",
      "ticker": "232140",
      "weight": 0.00825,
      "shares_held": 18559,
      "exchange": "Korea Exchange (Kosdaq)",
      "price": 15.7
    },
    {
      "name": "ZHEJIANG JINGSHENG MECHANICAL & EL",
      "ticker": "300316",
      "weight": 0.00509,
      "shares_held": 28200,
      "exchange": "Shenzhen Stock Exchange",
      "price": 6.37
    }
  ],
  "inception_date": "03-Aug-21",
  "isin": "IE000I8KRLL9",
  "issuing_company": "iShares IV plc",
  "methodology": "Replicated",
  "nav": "USD 16.70",
  "nav_total_return_ytd": "50.33%",
  "net_assets": "USD 3,482,239,519",
  "net_assets_of_fund": "USD 3,482,239,519",
  "number_of_holdings": "252",
  "price": 16.7,
  "price_book_ratio": "8.73",
  "price_earnings": "48.19",
  "product_structure": "Physical",
  "rebalance_frequency": "Quarterly",
  "securities_lending_return": "0.01%",
  "sfdr_classification": "Article 8",
  "share_class_currency": "USD",
  "shares_outstanding": "208,500,000",
  "standard_deviation_3y": "28.51%",
  "ticker": "SEMI",
  "total_expense_ratio": "0.35%",
  "ucits": "Yes",
  "use_of_income": "Accumulating"
}
