{
  "30_day_median_bid_ask_spread": "0.00%",
  "base_currency": "USD",
  "bid_ask": "$675.88",
  "closing_price": "$676.01",
  "date": "2026-04-08",
  "day_high": "$677.08",
  "day_low": "$671.46",
  "est_3_5_year_eps_growth": "14.19%",
  "exchange_volume_shares": "21,113,085",
  "holdings": [
    {
      "name": "3M CO",
      "ticker": "MMM",
      "weight": 0.134997,
      "shares_held": 6203877
    },
    {
      "name": "ABBOTT LABORATORIES",
      "ticker": "ABT",
      "weight": 0.309692,
      "shares_held": 20500190
    },
    {
      "name": "ABBVIE INC",
      "ticker": "ABBV",
      "weight": 0.643794,
      "shares_held": 20857975
    },
    {
      "name": "ACCENTURE PLC CL A",
      "ticker": "ACN",
      "weight": 0.203338,
      "shares_held": 7252077
    },
    {
      "name": "ADOBE INC",
      "ticker": "ADBE",
      "weight": 0.168865,
      "shares_held": 4837260
    },
    {
      "name": "ADVANCED MICRO DEVICES",
      "ticker": "AMD",
      "weight": 0.650733,
      "shares_held": 19242973
    },
    {
      "name": "AES CORP",
      "ticker": "AES",
      "weight": 0.017855,
      "shares_held": 8499793
    },
    {
      "name": "AFLAC INC",
      "ticker": "AFL",
      "weight": 0.090577,
      "shares_held": 5494878
    },
    {
      "name": "AGILENT TECHNOLOGIES INC",
      "ticker": "A",
      "weight": 0.057309,
      "shares_held": 3360129
    },
    {
      "name": "AIR PRODUCTS + CHEMICALS INC",
      "ticker": "APD",
      "weight": 0.113973,
      "shares_held": 2634132
    },
    {
      "name": "AIRBNB INC CLASS A",
      "ticker": "ABNB",
      "weight": 0.095581,
      "shares_held": 4986504
    },
    {
      "name": "AKAMAI TECHNOLOGIES INC",
      "ticker": "AKAM",
      "weight": 0.028601,
      "shares_held": 1690231
    },
    {
      "name": "ALBEMARLE CORP",
      "ticker": "ALB",
      "weight": 0.035836,
      "shares_held": 1384503
    },
    {
      "name": "ALEXANDRIA REAL ESTATE EQUIT",
      "ticker": "ARE",
      "weight": 0.012015,
      "shares_held": 1836870
    },
    {
      "name": "ALIGN TECHNOLOGY INC",
      "ticker": "ALGN",
      "weight": 0.02035,
      "shares_held": 788903
    },
    {
      "name": "ALLEGION PLC",
      "ticker": "ALLE",
      "weight": 0.021452,
      "shares_held": 1017759
    },
    {
      "name": "ALLIANT ENERGY CORP",
      "ticker": "LNT",
      "weight": 0.032141,
      "shares_held": 3018679
    },
    {
      "name": "ALLSTATE CORP",
      "ticker": "ALL",
      "weight": 0.09468,
      "shares_held": 3060539
    },
    {
      "name": "ALPHABET INC CL A",
      "ticker": "GOOGL",
      "weight": 3.179137,
      "shares_held": 68680304
    },
    {
      "name": "ALPHABET INC CL C",
      "ticker": "GOOG",
      "weight": 2.533505,
      "shares_held": 55181078
    },
    {
      "name": "ALTRIA GROUP INC",
      "ticker": "MO",
      "weight": 0.193276,
      "shares_held": 19834517
    },
    {
      "name": "AMAZON.COM INC",
      "ticker": "AMZN",
      "weight": 3.719356,
      "shares_held": 115240427
    },
    {
      "name": "AMCOR PLC",
      "ticker": "AMCR",
      "weight": 0.033752,
      "shares_held": 5460844
    },
    {
      "name": "AMEREN CORPORATION",
      "ticker": "AEE",
      "weight": 0.053682,
      "shares_held": 3260673
    },
    {
      "name": "AMERICAN ELECTRIC POWER",
      "ticker": "AEP",
      "weight": 0.125381,
      "shares_held": 6380461
    },
    {
      "name": "AMERICAN EXPRESS CO",
      "ticker": "AXP",
      "weight": 0.291341,
      "shares_held": 6313477
    },
    {
      "name": "AMERICAN INTERNATIONAL GROUP",
      "ticker": "AIG",
      "weight": 0.071292,
      "shares_held": 6311795
    },
    {
      "name": "AMERICAN TOWER CORP",
      "ticker": "AMT",
      "weight": 0.142004,
      "shares_held": 5525401
    },
    {
      "name": "AMERICAN WATER WORKS CO INC",
      "ticker": "AWK",
      "weight": 0.045929,
      "shares_held": 2308966
    },
    {
      "name": "AMERIPRISE FINANCIAL INC",
      "ticker": "AMP",
      "weight": 0.070985,
      "shares_held": 1073975
    },
    {
      "name": "AMETEK INC",
      "ticker": "AME",
      "weight": 0.091597,
      "shares_held": 2724260
    },
    {
      "name": "AMGEN INC",
      "ticker": "AMGN",
      "weight": 0.323945,
      "shares_held": 6348337
    },
    {
      "name": "AMPHENOL CORP CL A",
      "ticker": "APH",
      "weight": 0.286233,
      "shares_held": 14500360
    },
    {
      "name": "ANALOG DEVICES INC",
      "ticker": "ADI",
      "weight": 0.290889,
      "shares_held": 5759810
    },
    {
      "name": "AON PLC CLASS A",
      "ticker": "AON",
      "weight": 0.121527,
      "shares_held": 2526354
    },
    {
      "name": "APA CORP",
      "ticker": "APA",
      "weight": 0.023721,
      "shares_held": 4196491
    },
    {
      "name": "APOLLO GLOBAL MANAGEMENT INC",
      "ticker": "APO",
      "weight": 0.085799,
      "shares_held": 5494336
    },
    {
      "name": "APPLE INC",
      "ticker": "AAPL",
      "weight": 6.54103,
      "shares_held": 173194653
    },
    {
      "name": "APPLIED MATERIALS INC",
      "ticker": "AMAT",
      "weight": 0.526637,
      "shares_held": 9359644
    },
    {
      "name": "APPLOVIN CORP CLASS A",
      "ticker": "APP",
      "weight": 0.182598,
      "shares_held": 3199766
    },
    {
      "name": "APTIV PLC",
      "ticker": "APTV",
      "weight": 0.022067,
      "shares_held": 2490930
    },
    {
      "name": "ARCH CAPITAL GROUP LTD",
      "ticker": "ACGL",
      "weight": 0.060449,
      "shares_held": 4202750
    },
    {
      "name": "ARCHER DANIELS MIDLAND CO",
      "ticker": "ADM",
      "weight": 0.05928,
      "shares_held": 5666150
    },
    {
      "name": "ARES MANAGEMENT CORP   A",
      "ticker": "ARES",
      "weight": 0.03717,
      "shares_held": 2430700
    },
    {
      "name": "ARISTA NETWORKS INC",
      "ticker": "ANET",
      "weight": 0.257578,
      "shares_held": 12171728
    },
    {
      "name": "ARTHUR J GALLAGHER + CO",
      "ticker": "AJG",
      "weight": 0.097736,
      "shares_held": 3034416
    },
    {
      "name": "ASSURANT INC",
      "ticker": "AIZ",
      "weight": 0.019496,
      "shares_held": 597471
    },
    {
      "name": "AT+T INC",
      "ticker": "T",
      "weight": 0.329288,
      "shares_held": 82535048
    },
    {
      "name": "ATMOS ENERGY CORP",
      "ticker": "ATO",
      "weight": 0.053991,
      "shares_held": 1951490
    },
    {
      "name": "AUTODESK INC",
      "ticker": "ADSK",
      "weight": 0.087602,
      "shares_held": 2495454
    },
    {
      "name": "AUTOMATIC DATA PROCESSING",
      "ticker": "ADP",
      "weight": 0.13893,
      "shares_held": 4743479
    },
    {
      "name": "AUTOZONE INC",
      "ticker": "AZO",
      "weight": 0.098679,
      "shares_held": 195231
    },
    {
      "name": "AVALONBAY COMMUNITIES INC",
      "ticker": "AVB",
      "weight": 0.041136,
      "shares_held": 1673583
    },
    {
      "name": "AVERY DENNISON CORP",
      "ticker": "AVY",
      "weight": 0.023391,
      "shares_held": 914682
    },
    {
      "name": "AXON ENTERPRISE INC",
      "ticker": "AXON",
      "weight": 0.053071,
      "shares_held": 929208
    },
    {
      "name": "BAKER HUGHES CO",
      "ticker": "BKR",
      "weight": 0.107479,
      "shares_held": 11665418
    },
    {
      "name": "BALL CORP",
      "ticker": "BALL",
      "weight": 0.028728,
      "shares_held": 3171299
    },
    {
      "name": "BANK OF AMERICA CORP",
      "ticker": "BAC",
      "weight": 0.592672,
      "shares_held": 78313187
    },
    {
      "name": "BANK OF NEW YORK MELLON CORP",
      "ticker": "BK",
      "weight": 0.151306,
      "shares_held": 8107204
    },
    {
      "name": "BAXTER INTERNATIONAL INC",
      "ticker": "BAX",
      "weight": 0.015344,
      "shares_held": 6101394
    },
    {
      "name": "BECTON DICKINSON AND CO",
      "ticker": "BDX",
      "weight": 0.076785,
      "shares_held": 3350782
    },
    {
      "name": "BERKSHIRE HATHAWAY INC CL B",
      "ticker": "BRK.B",
      "weight": 1.514276,
      "shares_held": 21637669
    },
    {
      "name": "BEST BUY CO INC",
      "ticker": "BBY",
      "weight": 0.021744,
      "shares_held": 2311750
    },
    {
      "name": "BIO TECHNE CORP",
      "ticker": "TECH",
      "weight": 0.01485,
      "shares_held": 1843812
    },
    {
      "name": "BIOGEN INC",
      "ticker": "BIIB",
      "weight": 0.045611,
      "shares_held": 1738040
    },
    {
      "name": "BLACKROCK INC",
      "ticker": "BLK",
      "weight": 0.248487,
      "shares_held": 1700808
    },
    {
      "name": "BLACKSTONE INC",
      "ticker": "BX",
      "weight": 0.151596,
      "shares_held": 8831639
    },
    {
      "name": "BLOCK INC",
      "ticker": "XYZ",
      "weight": 0.059594,
      "shares_held": 6502116
    },
    {
      "name": "BOEING CO/THE",
      "ticker": "BA",
      "weight": 0.294551,
      "shares_held": 9270916
    },
    {
      "name": "BOOKING HOLDINGS INC",
      "ticker": "BKNG",
      "weight": 0.251217,
      "shares_held": 9514618
    },
    {
      "name": "BOSTON SCIENTIFIC CORP",
      "ticker": "BSX",
      "weight": 0.15974,
      "shares_held": 17503985
    },
    {
      "name": "BRISTOL MYERS SQUIBB CO",
      "ticker": "BMY",
      "weight": 0.207605,
      "shares_held": 24040103
    },
    {
      "name": "BROADCOM INC",
      "ticker": "AVGO",
      "weight": 2.860758,
      "shares_held": 55930978
    },
    {
      "name": "BROADRIDGE FINANCIAL SOLUTIO",
      "ticker": "BR",
      "weight": 0.032513,
      "shares_held": 1384631
    },
    {
      "name": "BROWN + BROWN INC",
      "ticker": "BRO",
      "weight": 0.034232,
      "shares_held": 3463239
    },
    {
      "name": "BROWN FORMAN CORP CLASS B",
      "ticker": "BF.B",
      "weight": 0.007971,
      "shares_held": 2035225
    },
    {
      "name": "BUILDERS FIRSTSOURCE INC",
      "ticker": "BLDR",
      "weight": 0.016,
      "shares_held": 1320050
    },
    {
      "name": "BUNGE GLOBAL SA",
      "ticker": "BG",
      "weight": 0.029708,
      "shares_held": 1601703
    },
    {
      "name": "BXP INC",
      "ticker": "BXP",
      "weight": 0.013315,
      "shares_held": 1737308
    },
    {
      "name": "C.H. ROBINSON WORLDWIDE INC",
      "ticker": "CHRW",
      "weight": 0.035279,
      "shares_held": 1402634
    },
    {
      "name": "CADENCE DESIGN SYS INC",
      "ticker": "CDNS",
      "weight": 0.135772,
      "shares_held": 3214998
    },
    {
      "name": "CAMDEN PROPERTY TRUST",
      "ticker": "CPT",
      "weight": 0.018197,
      "shares_held": 1219731
    },
    {
      "name": "CAPITAL ONE FINANCIAL CORP",
      "ticker": "COF",
      "weight": 0.206823,
      "shares_held": 7366795
    },
    {
      "name": "CARDINAL HEALTH INC",
      "ticker": "CAH",
      "weight": 0.086921,
      "shares_held": 2769757
    },
    {
      "name": "CARNIVAL CORP",
      "ticker": "CCL",
      "weight": 0.055476,
      "shares_held": 13567522
    },
    {
      "name": "CARRIER GLOBAL CORP",
      "ticker": "CARR",
      "weight": 0.078622,
      "shares_held": 9246328
    },
    {
      "name": "CARVANA CO",
      "ticker": "CVNA",
      "weight": 0.082716,
      "shares_held": 1673601
    },
    {
      "name": "CASEY S GENERAL STORES INC",
      "ticker": "CASY",
      "weight": 0.047862,
      "shares_held": 432640
    },
    {
      "name": "CATERPILLAR INC",
      "ticker": "CAT",
      "weight": 0.618093,
      "shares_held": 5491528
    },
    {
      "name": "CBOE GLOBAL MARKETS INC",
      "ticker": "CBOE",
      "weight": 0.053396,
      "shares_held": 1232663
    },
    {
      "name": "CBRE GROUP INC   A",
      "ticker": "CBRE",
      "weight": 0.071042,
      "shares_held": 3417829
    },
    {
      "name": "CDW CORP/DE",
      "ticker": "CDW",
      "weight": 0.028636,
      "shares_held": 1549018
    },
    {
      "name": "CENCORA INC",
      "ticker": "COR",
      "weight": 0.10875,
      "shares_held": 2294352
    },
    {
      "name": "CENTENE CORP",
      "ticker": "CNC",
      "weight": 0.029946,
      "shares_held": 5506669
    },
    {
      "name": "CENTERPOINT ENERGY INC",
      "ticker": "CNP",
      "weight": 0.048985,
      "shares_held": 7687723
    },
    {
      "name": "CF INDUSTRIES HOLDINGS INC",
      "ticker": "CF",
      "weight": 0.033969,
      "shares_held": 1845783
    },
    {
      "name": "CHARLES RIVER LABORATORIES",
      "ticker": "CRL",
      "weight": 0.014979,
      "shares_held": 586533
    },
    {
      "name": "CHARTER COMMUNICATIONS INC A",
      "ticker": "CHTR",
      "weight": 0.032641,
      "shares_held": 1009606
    },
    {
      "name": "CHEVRON CORP",
      "ticker": "CVX",
      "weight": 0.622468,
      "shares_held": 22122165
    },
    {
      "name": "CHIPOTLE MEXICAN GRILL INC",
      "ticker": "CMG",
      "weight": 0.075536,
      "shares_held": 15324530
    },
    {
      "name": "CHUBB LTD",
      "ticker": "CB",
      "weight": 0.208014,
      "shares_held": 4286858
    },
    {
      "name": "CHURCH + DWIGHT CO INC",
      "ticker": "CHD",
      "weight": 0.038181,
      "shares_held": 2778533
    },
    {
      "name": "CIENA CORP",
      "ticker": "CIEN",
      "weight": 0.119516,
      "shares_held": 1658480
    },
    {
      "name": "CINCINNATI FINANCIAL CORP",
      "ticker": "CINF",
      "weight": 0.043969,
      "shares_held": 1846330
    },
    {
      "name": "CINTAS CORP",
      "ticker": "CTAS",
      "weight": 0.10194,
      "shares_held": 4002624
    },
    {
      "name": "CISCO SYSTEMS INC",
      "ticker": "CSCO",
      "weight": 0.569282,
      "shares_held": 46625339
    },
    {
      "name": "CITIGROUP INC",
      "ticker": "C",
      "weight": 0.371129,
      "shares_held": 20602193
    },
    {
      "name": "CITIZENS FINANCIAL GROUP",
      "ticker": "CFG",
      "weight": 0.04643,
      "shares_held": 4990355
    },
    {
      "name": "CLOROX COMPANY",
      "ticker": "CLX",
      "weight": 0.022038,
      "shares_held": 1429675
    },
    {
      "name": "CME GROUP INC",
      "ticker": "CME",
      "weight": 0.187718,
      "shares_held": 4249680
    },
    {
      "name": "CMS ENERGY CORP",
      "ticker": "CMS",
      "weight": 0.04156,
      "shares_held": 3614588
    },
    {
      "name": "COCA COLA CO/THE",
      "ticker": "KO",
      "weight": 0.514711,
      "shares_held": 45652090
    },
    {
      "name": "COGNIZANT TECH SOLUTIONS A",
      "ticker": "CTSH",
      "weight": 0.050012,
      "shares_held": 5620385
    },
    {
      "name": "COHERENT CORP",
      "ticker": "COHR",
      "weight": 0.09091,
      "shares_held": 2211601
    },
    {
      "name": "COINBASE GLOBAL INC  CLASS A",
      "ticker": "COIN",
      "weight": 0.067041,
      "shares_held": 2624802
    },
    {
      "name": "COLGATE PALMOLIVE CO",
      "ticker": "CL",
      "weight": 0.119034,
      "shares_held": 9538288
    },
    {
      "name": "COMCAST CORP CLASS A",
      "ticker": "CMCSA",
      "weight": 0.172467,
      "shares_held": 42285340
    },
    {
      "name": "COMFORT SYSTEMS USA INC",
      "ticker": "FIX",
      "weight": 0.092531,
      "shares_held": 415904
    },
    {
      "name": "CONAGRA BRANDS INC",
      "ticker": "CAG",
      "weight": 0.012938,
      "shares_held": 5692663
    },
    {
      "name": "CONOCOPHILLIPS",
      "ticker": "COP",
      "weight": 0.263811,
      "shares_held": 14442424
    },
    {
      "name": "CONSOLIDATED EDISON INC",
      "ticker": "ED",
      "weight": 0.07068,
      "shares_held": 4266344
    },
    {
      "name": "CONSTELLATION BRANDS INC A",
      "ticker": "STZ",
      "weight": 0.036567,
      "shares_held": 1668270
    },
    {
      "name": "CONSTELLATION ENERGY",
      "ticker": "CEG",
      "weight": 0.152262,
      "shares_held": 3671824
    },
    {
      "name": "CONTRA HOLOGIC INCORPO",
      "ticker": "-",
      "weight": 0.000004,
      "shares_held": 2578626
    },
    {
      "name": "COOPER COS INC/THE",
      "ticker": "COO",
      "weight": 0.023997,
      "shares_held": 2293419
    },
    {
      "name": "COPART INC",
      "ticker": "CPRT",
      "weight": 0.050805,
      "shares_held": 10499910
    },
    {
      "name": "CORNING INC",
      "ticker": "GLW",
      "weight": 0.222189,
      "shares_held": 9225637
    },
    {
      "name": "CORPAY INC",
      "ticker": "CPAY",
      "weight": 0.036701,
      "shares_held": 827820
    },
    {
      "name": "CORTEVA INC",
      "ticker": "CTVA",
      "weight": 0.096959,
      "shares_held": 7916589
    },
    {
      "name": "COSTAR GROUP INC",
      "ticker": "CSGP",
      "weight": 0.028445,
      "shares_held": 5023029
    },
    {
      "name": "COSTCO WHOLESALE CORP",
      "ticker": "COST",
      "weight": 0.787369,
      "shares_held": 5238989
    },
    {
      "name": "COTERRA ENERGY INC",
      "ticker": "CTRA",
      "weight": 0.043828,
      "shares_held": 8979382
    },
    {
      "name": "CRH PLC",
      "ticker": "CRH",
      "weight": 0.131687,
      "shares_held": 7931294
    },
    {
      "name": "CROWDSTRIKE HOLDINGS INC   A",
      "ticker": "CRWD",
      "weight": 0.185225,
      "shares_held": 2977078
    },
    {
      "name": "CROWN CASTLE INC",
      "ticker": "CCI",
      "weight": 0.06413,
      "shares_held": 5140566
    },
    {
      "name": "CSX CORP",
      "ticker": "CSX",
      "weight": 0.135129,
      "shares_held": 21982393
    },
    {
      "name": "CUMMINS INC",
      "ticker": "CMI",
      "weight": 0.141765,
      "shares_held": 1628810
    },
    {
      "name": "CVS HEALTH CORP",
      "ticker": "CVS",
      "weight": 0.172413,
      "shares_held": 15000931
    },
    {
      "name": "DANAHER CORP",
      "ticker": "DHR",
      "weight": 0.21249,
      "shares_held": 7424759
    },
    {
      "name": "DARDEN RESTAURANTS INC",
      "ticker": "DRI",
      "weight": 0.038583,
      "shares_held": 1351890
    },
    {
      "name": "DATADOG INC   CLASS A",
      "ticker": "DDOG",
      "weight": 0.065981,
      "shares_held": 3882493
    },
    {
      "name": "DAVITA INC",
      "ticker": "DVA",
      "weight": 0.008338,
      "shares_held": 385047
    },
    {
      "name": "DECKERS OUTDOOR CORP",
      "ticker": "DECK",
      "weight": 0.025789,
      "shares_held": 1662319
    },
    {
      "name": "DEERE + CO",
      "ticker": "DE",
      "weight": 0.26455,
      "shares_held": 2976337
    },
    {
      "name": "DELL TECHNOLOGIES  C",
      "ticker": "DELL",
      "weight": 0.094626,
      "shares_held": 3497506
    },
    {
      "name": "DELTA AIR LINES INC",
      "ticker": "DAL",
      "weight": 0.076207,
      "shares_held": 7673501
    },
    {
      "name": "DEVON ENERGY CORP",
      "ticker": "DVN",
      "weight": 0.050951,
      "shares_held": 7290346
    },
    {
      "name": "DEXCOM INC",
      "ticker": "DXCM",
      "weight": 0.043393,
      "shares_held": 4520756
    },
    {
      "name": "DIAMONDBACK ENERGY INC",
      "ticker": "FANG",
      "weight": 0.062292,
      "shares_held": 2290037
    },
    {
      "name": "DIGITAL REALTY TRUST INC",
      "ticker": "DLR",
      "weight": 0.103468,
      "shares_held": 3821028
    },
    {
      "name": "DOLLAR GENERAL CORP",
      "ticker": "DG",
      "weight": 0.04653,
      "shares_held": 2592211
    },
    {
      "name": "DOLLAR TREE INC",
      "ticker": "DLTR",
      "weight": 0.033425,
      "shares_held": 2169414
    },
    {
      "name": "DOMINION ENERGY INC",
      "ticker": "D",
      "weight": 0.092913,
      "shares_held": 10078160
    },
    {
      "name": "DOMINO S PIZZA INC",
      "ticker": "DPZ",
      "weight": 0.020217,
      "shares_held": 368363
    },
    {
      "name": "DOORDASH INC   A",
      "ticker": "DASH",
      "weight": 0.103685,
      "shares_held": 4423301
    },
    {
      "name": "DOVER CORP",
      "ticker": "DOV",
      "weight": 0.050087,
      "shares_held": 1584550
    },
    {
      "name": "DOW INC",
      "ticker": "DOW",
      "weight": 0.048376,
      "shares_held": 8442717
    },
    {
      "name": "DR HORTON INC",
      "ticker": "DHI",
      "weight": 0.065957,
      "shares_held": 3168954
    },
    {
      "name": "DTE ENERGY COMPANY",
      "ticker": "DTE",
      "weight": 0.053078,
      "shares_held": 2445609
    },
    {
      "name": "DUKE ENERGY CORP",
      "ticker": "DUK",
      "weight": 0.176242,
      "shares_held": 9180669
    },
    {
      "name": "DUPONT DE NEMOURS INC",
      "ticker": "DD",
      "weight": 0.033484,
      "shares_held": 4797138
    },
    {
      "name": "EATON CORP PLC",
      "ticker": "ETN",
      "weight": 0.258028,
      "shares_held": 4587461
    },
    {
      "name": "EBAY INC",
      "ticker": "EBAY",
      "weight": 0.075523,
      "shares_held": 5348952
    },
    {
      "name": "ECHOSTAR CORP A",
      "ticker": "SATS",
      "weight": 0.028448,
      "shares_held": 1587842
    },
    {
      "name": "ECOLAB INC",
      "ticker": "ECL",
      "weight": 0.120046,
      "shares_held": 3008798
    },
    {
      "name": "EDISON INTERNATIONAL",
      "ticker": "EIX",
      "weight": 0.049459,
      "shares_held": 4560223
    },
    {
      "name": "EDWARDS LIFESCIENCES CORP",
      "ticker": "EW",
      "weight": 0.081851,
      "shares_held": 6867070
    },
    {
      "name": "ELECTRONIC ARTS INC",
      "ticker": "EA",
      "weight": 0.079255,
      "shares_held": 2663402
    },
    {
      "name": "ELEVANCE HEALTH INC",
      "ticker": "ELV",
      "weight": 0.120644,
      "shares_held": 2598876
    },
    {
      "name": "ELI LILLY + CO",
      "ticker": "LLY",
      "weight": 1.300318,
      "shares_held": 9350616
    },
    {
      "name": "EMCOR GROUP INC",
      "ticker": "EME",
      "weight": 0.060923,
      "shares_held": 529202
    },
    {
      "name": "EMERSON ELECTRIC CO",
      "ticker": "EMR",
      "weight": 0.138115,
      "shares_held": 6636819
    },
    {
      "name": "ENTERGY CORP",
      "ticker": "ETR",
      "weight": 0.08921,
      "shares_held": 5335968
    },
    {
      "name": "EOG RESOURCES INC",
      "ticker": "EOG",
      "weight": 0.129658,
      "shares_held": 6392161
    },
    {
      "name": "EPAM SYSTEMS INC",
      "ticker": "EPAM",
      "weight": 0.012376,
      "shares_held": 652652
    },
    {
      "name": "EQT CORP",
      "ticker": "EQT",
      "weight": 0.064777,
      "shares_held": 7378841
    },
    {
      "name": "EQUIFAX INC",
      "ticker": "EFX",
      "weight": 0.038007,
      "shares_held": 1413088
    },
    {
      "name": "EQUINIX INC",
      "ticker": "EQIX",
      "weight": 0.171976,
      "shares_held": 1158471
    },
    {
      "name": "EQUITY RESIDENTIAL",
      "ticker": "EQR",
      "weight": 0.035776,
      "shares_held": 4033732
    },
    {
      "name": "ERIE INDEMNITY COMPANY CL A",
      "ticker": "ERIE",
      "weight": 0.011025,
      "shares_held": 298295
    },
    {
      "name": "ESSEX PROPERTY TRUST INC",
      "ticker": "ESS",
      "weight": 0.027758,
      "shares_held": 755416
    },
    {
      "name": "ESTEE LAUDER COMPANIES CL A",
      "ticker": "EL",
      "weight": 0.030202,
      "shares_held": 2898123
    },
    {
      "name": "EVEREST GROUP LTD",
      "ticker": "EG",
      "weight": 0.023147,
      "shares_held": 476136
    },
    {
      "name": "EVERGY INC",
      "ticker": "EVRG",
      "weight": 0.033252,
      "shares_held": 2731886
    },
    {
      "name": "EVERSOURCE ENERGY",
      "ticker": "ES",
      "weight": 0.04505,
      "shares_held": 4414944
    },
    {
      "name": "EXELON CORP",
      "ticker": "EXC",
      "weight": 0.086549,
      "shares_held": 12066546
    },
    {
      "name": "EXPAND ENERGY CORP",
      "ticker": "EXE",
      "weight": 0.041134,
      "shares_held": 2814455
    },
    {
      "name": "EXPEDIA GROUP INC",
      "ticker": "EXPE",
      "weight": 0.047853,
      "shares_held": 1384720
    },
    {
      "name": "EXPEDITORS INTL WASH INC",
      "ticker": "EXPD",
      "weight": 0.033922,
      "shares_held": 1586014
    },
    {
      "name": "EXTRA SPACE STORAGE INC",
      "ticker": "EXR",
      "weight": 0.050452,
      "shares_held": 2511128
    },
    {
      "name": "EXXON MOBIL CORP",
      "ticker": "XOM",
      "weight": 1.123761,
      "shares_held": 49312595
    },
    {
      "name": "F5 INC",
      "ticker": "FFIV",
      "weight": 0.029443,
      "shares_held": 662278
    },
    {
      "name": "FACTSET RESEARCH SYSTEMS INC",
      "ticker": "FDS",
      "weight": 0.014416,
      "shares_held": 443210
    },
    {
      "name": "FAIR ISAAC CORP",
      "ticker": "FICO",
      "weight": 0.04469,
      "shares_held": 280537
    },
    {
      "name": "FASTENAL CO",
      "ticker": "FAST",
      "weight": 0.095451,
      "shares_held": 13581016
    },
    {
      "name": "FEDERAL REALTY INVS TRUST",
      "ticker": "FRT",
      "weight": 0.014524,
      "shares_held": 927166
    },
    {
      "name": "FEDEX CORP",
      "ticker": "FDX",
      "weight": 0.138806,
      "shares_held": 2548113
    },
    {
      "name": "FIDELITY NATIONAL INFO SERV",
      "ticker": "FIS",
      "weight": 0.04202,
      "shares_held": 6127607
    },
    {
      "name": "FIFTH THIRD BANCORP",
      "ticker": "FITB",
      "weight": 0.076502,
      "shares_held": 10629077
    },
    {
      "name": "FIRST SOLAR INC",
      "ticker": "FSLR",
      "weight": 0.036973,
      "shares_held": 1262374
    },
    {
      "name": "FIRSTENERGY CORP",
      "ticker": "FE",
      "weight": 0.045888,
      "shares_held": 6120115
    },
    {
      "name": "FISERV INC",
      "ticker": "FISV",
      "weight": 0.052579,
      "shares_held": 6364781
    },
    {
      "name": "FORD MOTOR CO",
      "ticker": "F",
      "weight": 0.082177,
      "shares_held": 46251221
    },
    {
      "name": "FORTINET INC",
      "ticker": "FTNT",
      "weight": 0.091123,
      "shares_held": 7480151
    },
    {
      "name": "FORTIVE CORP",
      "ticker": "FTV",
      "weight": 0.03182,
      "shares_held": 3673465
    },
    {
      "name": "FOX CORP   CLASS A",
      "ticker": "FOXA",
      "weight": 0.0206,
      "shares_held": 2344985
    },
    {
      "name": "FOX CORP   CLASS B",
      "ticker": "FOX",
      "weight": 0.013071,
      "shares_held": 1644743
    },
    {
      "name": "FRANKLIN RESOURCES INC",
      "ticker": "BEN",
      "weight": 0.013387,
      "shares_held": 3688508
    },
    {
      "name": "FREEPORT MCMORAN INC",
      "ticker": "FCX",
      "weight": 0.161379,
      "shares_held": 16993611
    },
    {
      "name": "GARMIN LTD",
      "ticker": "GRMN",
      "weight": 0.071404,
      "shares_held": 1936352
    },
    {
      "name": "GARTNER INC",
      "ticker": "IT",
      "weight": 0.017934,
      "shares_held": 822897
    },
    {
      "name": "GE HEALTHCARE TECHNOLOGY",
      "ticker": "GEHC",
      "weight": 0.058096,
      "shares_held": 5400148
    },
    {
      "name": "GE VERNOVA INC",
      "ticker": "GEV",
      "weight": 0.433967,
      "shares_held": 3178112
    },
    {
      "name": "GEN DIGITAL INC",
      "ticker": "GEN",
      "weight": 0.018223,
      "shares_held": 6613272
    },
    {
      "name": "GENERAC HOLDINGS INC",
      "ticker": "GNRC",
      "weight": 0.020293,
      "shares_held": 685513
    },
    {
      "name": "GENERAL DYNAMICS CORP",
      "ticker": "GD",
      "weight": 0.153187,
      "shares_held": 3000204
    },
    {
      "name": "GENERAL ELECTRIC",
      "ticker": "GE",
      "weight": 0.555785,
      "shares_held": 12367780
    },
    {
      "name": "GENERAL MILLS INC",
      "ticker": "GIS",
      "weight": 0.033745,
      "shares_held": 6320487
    },
    {
      "name": "GENERAL MOTORS CO",
      "ticker": "GM",
      "weight": 0.119176,
      "shares_held": 10646054
    },
    {
      "name": "GENUINE PARTS CO",
      "ticker": "GPC",
      "weight": 0.025624,
      "shares_held": 1635402
    },
    {
      "name": "GILEAD SCIENCES INC",
      "ticker": "GILD",
      "weight": 0.301995,
      "shares_held": 14626528
    },
    {
      "name": "GLOBAL PAYMENTS INC",
      "ticker": "GPN",
      "weight": 0.026592,
      "shares_held": 2801537
    },
    {
      "name": "GLOBE LIFE INC",
      "ticker": "GL",
      "weight": 0.020094,
      "shares_held": 931663
    },
    {
      "name": "GODADDY INC   CLASS A",
      "ticker": "GDDY",
      "weight": 0.018854,
      "shares_held": 1599179
    },
    {
      "name": "GOLDMAN SACHS GROUP INC",
      "ticker": "GS",
      "weight": 0.467233,
      "shares_held": 3536270
    },
    {
      "name": "HALLIBURTON CO",
      "ticker": "HAL",
      "weight": 0.054296,
      "shares_held": 9846761
    },
    {
      "name": "HARTFORD INSURANCE GROUP INC",
      "ticker": "HIG",
      "weight": 0.066815,
      "shares_held": 3297574
    },
    {
      "name": "HASBRO INC",
      "ticker": "HAS",
      "weight": 0.021459,
      "shares_held": 1567465
    },
    {
      "name": "HCA HEALTHCARE INC",
      "ticker": "HCA",
      "weight": 0.135869,
      "shares_held": 1843931
    },
    {
      "name": "HEALTHPEAK PROPERTIES INC",
      "ticker": "DOC",
      "weight": 0.019801,
      "shares_held": 8138072
    },
    {
      "name": "HENRY SCHEIN INC",
      "ticker": "HSIC",
      "weight": 0.013048,
      "shares_held": 1184241
    },
    {
      "name": "HERSHEY CO/THE",
      "ticker": "HSY",
      "weight": 0.053226,
      "shares_held": 1745906
    },
    {
      "name": "HEWLETT PACKARD ENTERPRISE",
      "ticker": "HPE",
      "weight": 0.056904,
      "shares_held": 15616023
    },
    {
      "name": "HILTON WORLDWIDE HOLDINGS IN",
      "ticker": "HLT",
      "weight": 0.124946,
      "shares_held": 2700293
    },
    {
      "name": "HOME DEPOT INC",
      "ticker": "HD",
      "weight": 0.575672,
      "shares_held": 11739492
    },
    {
      "name": "HONEYWELL INTERNATIONAL INC",
      "ticker": "HON",
      "weight": 0.253779,
      "shares_held": 7483574
    },
    {
      "name": "HORMEL FOODS CORP",
      "ticker": "HRL",
      "weight": 0.010967,
      "shares_held": 3474308
    },
    {
      "name": "HOST HOTELS + RESORTS INC",
      "ticker": "HST",
      "weight": 0.02167,
      "shares_held": 7536820
    },
    {
      "name": "HOWMET AEROSPACE INC",
      "ticker": "HWM",
      "weight": 0.172278,
      "shares_held": 4724001
    },
    {
      "name": "HP INC",
      "ticker": "HPQ",
      "weight": 0.029646,
      "shares_held": 10758515
    },
    {
      "name": "HUBBELL INC",
      "ticker": "HUBB",
      "weight": 0.048133,
      "shares_held": 625869
    },
    {
      "name": "HUMANA INC",
      "ticker": "HUM",
      "weight": 0.041159,
      "shares_held": 1422201
    },
    {
      "name": "HUNT (JB) TRANSPRT SVCS INC",
      "ticker": "JBHT",
      "weight": 0.02915,
      "shares_held": 889595
    },
    {
      "name": "HUNTINGTON BANCSHARES INC",
      "ticker": "HBAN",
      "weight": 0.057313,
      "shares_held": 24030039
    },
    {
      "name": "HUNTINGTON INGALLS INDUSTRIE",
      "ticker": "HII",
      "weight": 0.027657,
      "shares_held": 460902
    },
    {
      "name": "IDEX CORP",
      "ticker": "IEX",
      "weight": 0.025561,
      "shares_held": 885662
    },
    {
      "name": "IDEXX LABORATORIES INC",
      "ticker": "IDXX",
      "weight": 0.08128,
      "shares_held": 941457
    },
    {
      "name": "ILLINOIS TOOL WORKS",
      "ticker": "ITW",
      "weight": 0.121443,
      "shares_held": 3088995
    },
    {
      "name": "INCYTE CORP",
      "ticker": "INCY",
      "weight": 0.027401,
      "shares_held": 1958872
    },
    {
      "name": "INGERSOLL RAND INC",
      "ticker": "IR",
      "weight": 0.051662,
      "shares_held": 4182775
    },
    {
      "name": "INSULET CORP",
      "ticker": "PODD",
      "weight": 0.024621,
      "shares_held": 829349
    },
    {
      "name": "INTEL CORP",
      "ticker": "INTC",
      "weight": 0.476296,
      "shares_held": 55387751
    },
    {
      "name": "INTERACTIVE BROKERS GRO CL A",
      "ticker": "IBKR",
      "weight": 0.055525,
      "shares_held": 5263911
    },
    {
      "name": "INTERCONTINENTAL EXCHANGE IN",
      "ticker": "ICE",
      "weight": 0.163766,
      "shares_held": 6690805
    },
    {
      "name": "INTERNATIONAL PAPER CO",
      "ticker": "IP",
      "weight": 0.033589,
      "shares_held": 6211538
    },
    {
      "name": "INTL BUSINESS MACHINES CORP",
      "ticker": "IBM",
      "weight": 0.38866,
      "shares_held": 11021522
    },
    {
      "name": "INTL FLAVORS + FRAGRANCES",
      "ticker": "IFF",
      "weight": 0.03238,
      "shares_held": 3008932
    },
    {
      "name": "INTUIT INC",
      "ticker": "INTU",
      "weight": 0.185785,
      "shares_held": 3279839
    },
    {
      "name": "INTUITIVE SURGICAL INC",
      "ticker": "ISRG",
      "weight": 0.282385,
      "shares_held": 4187527
    },
    {
      "name": "INVESCO LTD",
      "ticker": "IVZ",
      "weight": 0.018447,
      "shares_held": 5223514
    },
    {
      "name": "INVITATION HOMES INC",
      "ticker": "INVH",
      "weight": 0.025068,
      "shares_held": 6658031
    },
    {
      "name": "IQVIA HOLDINGS INC",
      "ticker": "IQV",
      "weight": 0.050597,
      "shares_held": 2010294
    },
    {
      "name": "IRON MOUNTAIN INC",
      "ticker": "IRM",
      "weight": 0.054322,
      "shares_held": 3481226
    },
    {
      "name": "JABIL INC",
      "ticker": "JBL",
      "weight": 0.05196,
      "shares_held": 1240493
    },
    {
      "name": "JACK HENRY + ASSOCIATES INC",
      "ticker": "JKHY",
      "weight": 0.019738,
      "shares_held": 856478
    },
    {
      "name": "JACOBS SOLUTIONS INC",
      "ticker": "J",
      "weight": 0.02686,
      "shares_held": 1404074
    },
    {
      "name": "JM SMUCKER CO/THE",
      "ticker": "SJM",
      "weight": 0.017407,
      "shares_held": 1272297
    },
    {
      "name": "JOHNSON + JOHNSON",
      "ticker": "JNJ",
      "weight": 1.001004,
      "shares_held": 28437999
    },
    {
      "name": "JOHNSON CONTROLS INTERNATION",
      "ticker": "JCI",
      "weight": 0.146641,
      "shares_held": 7232020
    },
    {
      "name": "JPMORGAN CHASE + CO",
      "ticker": "JPM",
      "weight": 1.429277,
      "shares_held": 31814744
    },
    {
      "name": "KENVUE INC",
      "ticker": "KVUE",
      "weight": 0.057274,
      "shares_held": 22642824
    },
    {
      "name": "KEURIG DR PEPPER INC",
      "ticker": "KDP",
      "weight": 0.060437,
      "shares_held": 16033537
    },
    {
      "name": "KEYCORP",
      "ticker": "KEY",
      "weight": 0.034191,
      "shares_held": 11009230
    },
    {
      "name": "KEYSIGHT TECHNOLOGIES IN",
      "ticker": "KEYS",
      "weight": 0.093752,
      "shares_held": 2018933
    },
    {
      "name": "KIMBERLY CLARK CORP",
      "ticker": "KMB",
      "weight": 0.055543,
      "shares_held": 3925371
    },
    {
      "name": "KIMCO REALTY CORP",
      "ticker": "KIM",
      "weight": 0.02648,
      "shares_held": 8007335
    },
    {
      "name": "KINDER MORGAN INC",
      "ticker": "KMI",
      "weight": 0.111258,
      "shares_held": 23140121
    },
    {
      "name": "KKR + CO INC",
      "ticker": "KKR",
      "weight": 0.111329,
      "shares_held": 8122392
    },
    {
      "name": "KLA CORP",
      "ticker": "KLAC",
      "weight": 0.376969,
      "shares_held": 1545261
    },
    {
      "name": "KRAFT HEINZ CO/THE",
      "ticker": "KHC",
      "weight": 0.033713,
      "shares_held": 10070025
    },
    {
      "name": "KROGER CO",
      "ticker": "KR",
      "weight": 0.070913,
      "shares_held": 6850620
    },
    {
      "name": "L3HARRIS TECHNOLOGIES INC",
      "ticker": "LHX",
      "weight": 0.116677,
      "shares_held": 2209703
    },
    {
      "name": "LABCORP HOLDINGS INC",
      "ticker": "LH",
      "weight": 0.039391,
      "shares_held": 982935
    },
    {
      "name": "LAM RESEARCH CORP",
      "ticker": "LRCX",
      "weight": 0.529474,
      "shares_held": 14725363
    },
    {
      "name": "LAS VEGAS SANDS CORP",
      "ticker": "LVS",
      "weight": 0.028671,
      "shares_held": 3599790
    },
    {
      "name": "LEIDOS HOLDINGS INC",
      "ticker": "LDOS",
      "weight": 0.035519,
      "shares_held": 1515730
    },
    {
      "name": "LENNAR CORP W/D",
      "ticker": "LEN",
      "weight": 0.033008,
      "shares_held": 2553044
    },
    {
      "name": "LENNOX INTERNATIONAL INC",
      "ticker": "LII",
      "weight": 0.026172,
      "shares_held": 375287
    },
    {
      "name": "LINDE PLC",
      "ticker": "LIN",
      "weight": 0.401968,
      "shares_held": 5505859
    },
    {
      "name": "LIVE NATION ENTERTAINMENT IN",
      "ticker": "LYV",
      "weight": 0.044666,
      "shares_held": 1872075
    },
    {
      "name": "LOCKHEED MARTIN CORP",
      "ticker": "LMT",
      "weight": 0.2188,
      "shares_held": 2386507
    },
    {
      "name": "LOEWS CORP",
      "ticker": "L",
      "weight": 0.032152,
      "shares_held": 2007562
    },
    {
      "name": "LOWE S COS INC",
      "ticker": "LOW",
      "weight": 0.235438,
      "shares_held": 6623897
    },
    {
      "name": "LULULEMON ATHLETICA INC",
      "ticker": "LULU",
      "weight": 0.029581,
      "shares_held": 1276477
    },
    {
      "name": "LUMENTUM HOLDINGS INC",
      "ticker": "LITE",
      "weight": 0.110125,
      "shares_held": 842538
    },
    {
      "name": "LYONDELLBASELL INDU CL A",
      "ticker": "LYB",
      "weight": 0.032991,
      "shares_held": 3047133
    },
    {
      "name": "M + T BANK CORP",
      "ticker": "MTB",
      "weight": 0.057015,
      "shares_held": 1784366
    },
    {
      "name": "MARATHON PETROLEUM CORP",
      "ticker": "MPC",
      "weight": 0.117582,
      "shares_held": 3474653
    },
    {
      "name": "MARRIOTT INTERNATIONAL  CL A",
      "ticker": "MAR",
      "weight": 0.131726,
      "shares_held": 2590526
    },
    {
      "name": "MARSH + MCLENNAN COS",
      "ticker": "MRSH",
      "weight": 0.145526,
      "shares_held": 5703560
    },
    {
      "name": "MARTIN MARIETTA MATERIALS",
      "ticker": "MLM",
      "weight": 0.064959,
      "shares_held": 713219
    },
    {
      "name": "MASCO CORP",
      "ticker": "MAS",
      "weight": 0.021603,
      "shares_held": 2379776
    },
    {
      "name": "MASTERCARD INC   A",
      "ticker": "MA",
      "weight": 0.709776,
      "shares_held": 9611185
    },
    {
      "name": "MCCORMICK + CO NON VTG SHRS",
      "ticker": "MKC",
      "weight": 0.022073,
      "shares_held": 2995759
    },
    {
      "name": "MCDONALD S CORP",
      "ticker": "MCD",
      "weight": 0.376041,
      "shares_held": 8396582
    },
    {
      "name": "MCKESSON CORP",
      "ticker": "MCK",
      "weight": 0.183423,
      "shares_held": 1443334
    },
    {
      "name": "MEDTRONIC PLC",
      "ticker": "MDT",
      "weight": 0.195377,
      "shares_held": 15108318
    },
    {
      "name": "MERCK + CO. INC.",
      "ticker": "MRK",
      "weight": 0.526386,
      "shares_held": 29294418
    },
    {
      "name": "META PLATFORMS INC CLASS A",
      "ticker": "META",
      "weight": 2.305512,
      "shares_held": 25807047
    },
    {
      "name": "METLIFE INC",
      "ticker": "MET",
      "weight": 0.070209,
      "shares_held": 6474277
    },
    {
      "name": "METTLER TOLEDO INTERNATIONAL",
      "ticker": "MTD",
      "weight": 0.046643,
      "shares_held": 241727
    },
    {
      "name": "MGM RESORTS INTERNATIONAL",
      "ticker": "MGM",
      "weight": 0.012061,
      "shares_held": 2228519
    },
    {
      "name": "MICROCHIP TECHNOLOGY INC",
      "ticker": "MCHP",
      "weight": 0.066085,
      "shares_held": 6405025
    },
    {
      "name": "MICRON TECHNOLOGY INC",
      "ticker": "MU",
      "weight": 0.78775,
      "shares_held": 13277072
    },
    {
      "name": "MICROSOFT CORP",
      "ticker": "MSFT",
      "weight": 4.783411,
      "shares_held": 87599857
    },
    {
      "name": "MID AMERICA APARTMENT COMM",
      "ticker": "MAA",
      "weight": 0.02555,
      "shares_held": 1389084
    },
    {
      "name": "MODERNA INC",
      "ticker": "MRNA",
      "weight": 0.031177,
      "shares_held": 4102159
    },
    {
      "name": "MOLSON COORS BEVERAGE CO   B",
      "ticker": "TAP",
      "weight": 0.012634,
      "shares_held": 1972925
    },
    {
      "name": "MONDELEZ INTERNATIONAL INC A",
      "ticker": "MDLZ",
      "weight": 0.12957,
      "shares_held": 15098255
    },
    {
      "name": "MONOLITHIC POWER SYSTEMS INC",
      "ticker": "MPWR",
      "weight": 0.110021,
      "shares_held": 574446
    },
    {
      "name": "MONSTER BEVERAGE CORP",
      "ticker": "MNST",
      "weight": 0.092437,
      "shares_held": 8433229
    },
    {
      "name": "MOODY S CORP",
      "ticker": "MCO",
      "weight": 0.118552,
      "shares_held": 1815599
    },
    {
      "name": "MORGAN STANLEY",
      "ticker": "MS",
      "weight": 0.3642,
      "shares_held": 14183982
    },
    {
      "name": "MOSAIC CO/THE",
      "ticker": "MOS",
      "weight": 0.014619,
      "shares_held": 3764643
    },
    {
      "name": "MOTOROLA SOLUTIONS INC",
      "ticker": "MSI",
      "weight": 0.127435,
      "shares_held": 1951165
    },
    {
      "name": "MSCI INC",
      "ticker": "MSCI",
      "weight": 0.070237,
      "shares_held": 864537
    },
    {
      "name": "NASDAQ INC",
      "ticker": "NDAQ",
      "weight": 0.067877,
      "shares_held": 5282239
    },
    {
      "name": "NETAPP INC",
      "ticker": "NTAP",
      "weight": 0.033716,
      "shares_held": 2323626
    },
    {
      "name": "NETFLIX INC",
      "ticker": "NFLX",
      "weight": 0.722424,
      "shares_held": 49827615
    },
    {
      "name": "NEWMONT CORP",
      "ticker": "NEM",
      "weight": 0.222117,
      "shares_held": 12887492
    },
    {
      "name": "NEWS CORP   CLASS A",
      "ticker": "NWSA",
      "weight": 0.016085,
      "shares_held": 4430110
    },
    {
      "name": "NEWS CORP   CLASS B",
      "ticker": "NWS",
      "weight": 0.006006,
      "shares_held": 1434484
    },
    {
      "name": "NEXTERA ENERGY INC",
      "ticker": "NEE",
      "weight": 0.337286,
      "shares_held": 24553101
    },
    {
      "name": "NIKE INC  CL B",
      "ticker": "NKE",
      "weight": 0.088338,
      "shares_held": 14040659
    },
    {
      "name": "NISOURCE INC",
      "ticker": "NI",
      "weight": 0.039435,
      "shares_held": 5620285
    },
    {
      "name": "NORDSON CORP",
      "ticker": "NDSN",
      "weight": 0.025232,
      "shares_held": 629961
    },
    {
      "name": "NORFOLK SOUTHERN CORP",
      "ticker": "NSC",
      "weight": 0.113925,
      "shares_held": 2655490
    },
    {
      "name": "NORTHERN TRUST CORP",
      "ticker": "NTRS",
      "weight": 0.048439,
      "shares_held": 2188358
    },
    {
      "name": "NORTHROP GRUMMAN CORP",
      "ticker": "NOC",
      "weight": 0.157656,
      "shares_held": 1572093
    },
    {
      "name": "NORWEGIAN CRUISE LINE HOLDIN",
      "ticker": "NCLH",
      "weight": 0.015989,
      "shares_held": 5436829
    },
    {
      "name": "NRG ENERGY INC",
      "ticker": "NRG",
      "weight": 0.0587,
      "shares_held": 2510279
    },
    {
      "name": "NUCOR CORP",
      "ticker": "NUE",
      "weight": 0.071692,
      "shares_held": 2697975
    },
    {
      "name": "NVIDIA CORP",
      "ticker": "NVDA",
      "weight": 7.614206,
      "shares_held": 286670335
    },
    {
      "name": "NVR INC",
      "ticker": "NVR",
      "weight": 0.032365,
      "shares_held": 32843
    },
    {
      "name": "NXP SEMICONDUCTORS NV",
      "ticker": "NXPI",
      "weight": 0.088473,
      "shares_held": 2969124
    },
    {
      "name": "O REILLY AUTOMOTIVE INC",
      "ticker": "ORLY",
      "weight": 0.134622,
      "shares_held": 9916867
    },
    {
      "name": "OCCIDENTAL PETROLEUM CORP",
      "ticker": "OXY",
      "weight": 0.073908,
      "shares_held": 8476745
    },
    {
      "name": "OLD DOMINION FREIGHT LINE",
      "ticker": "ODFL",
      "weight": 0.065661,
      "shares_held": 2168941
    },
    {
      "name": "OMNICOM GROUP",
      "ticker": "OMC",
      "weight": 0.041423,
      "shares_held": 3694077
    },
    {
      "name": "ON SEMICONDUCTOR",
      "ticker": "ON",
      "weight": 0.046144,
      "shares_held": 4625970
    },
    {
      "name": "ONEOK INC",
      "ticker": "OKE",
      "weight": 0.093926,
      "shares_held": 7420556
    },
    {
      "name": "ORACLE CORP",
      "ticker": "ORCL",
      "weight": 0.417736,
      "shares_held": 20003238
    },
    {
      "name": "OTIS WORLDWIDE CORP",
      "ticker": "OTIS",
      "weight": 0.053511,
      "shares_held": 4611327
    },
    {
      "name": "P G + E CORP",
      "ticker": "PCG",
      "weight": 0.069726,
      "shares_held": 25991594
    },
    {
      "name": "PACCAR INC",
      "ticker": "PCAR",
      "weight": 0.112407,
      "shares_held": 6204791
    },
    {
      "name": "PACKAGING CORP OF AMERICA",
      "ticker": "PKG",
      "weight": 0.032346,
      "shares_held": 1050658
    },
    {
      "name": "PALANTIR TECHNOLOGIES INC A",
      "ticker": "PLTR",
      "weight": 0.553141,
      "shares_held": 26938728
    },
    {
      "name": "PALO ALTO NETWORKS INC",
      "ticker": "PANW",
      "weight": 0.241648,
      "shares_held": 9532415
    },
    {
      "name": "PARAMOUNT SKYDANCE CL B",
      "ticker": "PSKY",
      "weight": 0.005831,
      "shares_held": 3694148
    },
    {
      "name": "PARKER HANNIFIN CORP",
      "ticker": "PH",
      "weight": 0.209589,
      "shares_held": 1487268
    },
    {
      "name": "PAYCHEX INC",
      "ticker": "PAYX",
      "weight": 0.050255,
      "shares_held": 3832533
    },
    {
      "name": "PAYPAL HOLDINGS INC",
      "ticker": "PYPL",
      "weight": 0.07244,
      "shares_held": 10830815
    },
    {
      "name": "PENTAIR PLC",
      "ticker": "PNR",
      "weight": 0.025573,
      "shares_held": 1936435
    },
    {
      "name": "PEPSICO INC",
      "ticker": "PEP",
      "weight": 0.363857,
      "shares_held": 16113119
    },
    {
      "name": "PFIZER INC",
      "ticker": "PFE",
      "weight": 0.269182,
      "shares_held": 67174952
    },
    {
      "name": "PHILIP MORRIS INTERNATIONAL",
      "ticker": "PM",
      "weight": 0.430924,
      "shares_held": 18355100
    },
    {
      "name": "PHILLIPS 66",
      "ticker": "PSX",
      "weight": 0.116562,
      "shares_held": 4756296
    },
    {
      "name": "PINNACLE WEST CAPITAL",
      "ticker": "PNW",
      "weight": 0.021448,
      "shares_held": 1425839
    },
    {
      "name": "PNC FINANCIAL SERVICES GROUP",
      "ticker": "PNC",
      "weight": 0.153437,
      "shares_held": 4764645
    },
    {
      "name": "POOL CORP",
      "ticker": "POOL",
      "weight": 0.011822,
      "shares_held": 386945
    },
    {
      "name": "PPG INDUSTRIES INC",
      "ticker": "PPG",
      "weight": 0.042578,
      "shares_held": 2642193
    },
    {
      "name": "PPL CORP",
      "ticker": "PPL",
      "weight": 0.049753,
      "shares_held": 8711818
    },
    {
      "name": "PRINCIPAL FINANCIAL GROUP",
      "ticker": "PFG",
      "weight": 0.031871,
      "shares_held": 2319363
    },
    {
      "name": "PROCTER + GAMBLE CO/THE",
      "ticker": "PG",
      "weight": 0.579288,
      "shares_held": 27406070
    },
    {
      "name": "PROGRESSIVE CORP",
      "ticker": "PGR",
      "weight": 0.200083,
      "shares_held": 6924176
    },
    {
      "name": "PROLOGIS INC",
      "ticker": "PLD",
      "weight": 0.219604,
      "shares_held": 10955754
    },
    {
      "name": "PRUDENTIAL FINANCIAL INC",
      "ticker": "PRU",
      "weight": 0.057676,
      "shares_held": 4090837
    },
    {
      "name": "PTC INC",
      "ticker": "PTC",
      "weight": 0.029799,
      "shares_held": 1415470
    },
    {
      "name": "PUBLIC SERVICE ENTERPRISE GP",
      "ticker": "PEG",
      "weight": 0.071085,
      "shares_held": 5892448
    },
    {
      "name": "PUBLIC STORAGE",
      "ticker": "PSA",
      "weight": 0.079034,
      "shares_held": 1868251
    },
    {
      "name": "PULTEGROUP INC",
      "ticker": "PHM",
      "weight": 0.03963,
      "shares_held": 2255677
    },
    {
      "name": "QNITY ELECTRONICS INC",
      "ticker": "Q",
      "weight": 0.046947,
      "shares_held": 2488253
    },
    {
      "name": "QUALCOMM INC",
      "ticker": "QCOM",
      "weight": 0.233937,
      "shares_held": 12576958
    },
    {
      "name": "QUANTA SERVICES INC",
      "ticker": "PWR",
      "weight": 0.148133,
      "shares_held": 1762251
    },
    {
      "name": "QUEST DIAGNOSTICS INC",
      "ticker": "DGX",
      "weight": 0.03744,
      "shares_held": 1290959
    },
    {
      "name": "RALPH LAUREN CORP",
      "ticker": "RL",
      "weight": 0.02497,
      "shares_held": 455973
    },
    {
      "name": "RAYMOND JAMES FINANCIAL INC",
      "ticker": "RJF",
      "weight": 0.044978,
      "shares_held": 2085880
    },
    {
      "name": "REALTY INCOME CORP",
      "ticker": "O",
      "weight": 0.099705,
      "shares_held": 10885424
    },
    {
      "name": "REGENCY CENTERS CORP",
      "ticker": "REG",
      "weight": 0.022173,
      "shares_held": 1952257
    },
    {
      "name": "REGENERON PHARMACEUTICALS",
      "ticker": "REGN",
      "weight": 0.134919,
      "shares_held": 1192602
    },
    {
      "name": "REGIONS FINANCIAL CORP",
      "ticker": "RF",
      "weight": 0.040824,
      "shares_held": 10187723
    },
    {
      "name": "REPUBLIC SERVICES INC",
      "ticker": "RSG",
      "weight": 0.075206,
      "shares_held": 2381208
    },
    {
      "name": "RESMED INC",
      "ticker": "RMD",
      "weight": 0.057886,
      "shares_held": 1720080
    },
    {
      "name": "REVVITY INC",
      "ticker": "RVTY",
      "weight": 0.017515,
      "shares_held": 1328186
    },
    {
      "name": "ROBINHOOD MARKETS INC   A",
      "ticker": "HOOD",
      "weight": 0.097516,
      "shares_held": 9306542
    },
    {
      "name": "ROCKWELL AUTOMATION INC",
      "ticker": "ROK",
      "weight": 0.07567,
      "shares_held": 1330185
    },
    {
      "name": "ROLLINS INC",
      "ticker": "ROL",
      "weight": 0.027556,
      "shares_held": 3453359
    },
    {
      "name": "ROPER TECHNOLOGIES INC",
      "ticker": "ROP",
      "weight": 0.065085,
      "shares_held": 1253823
    },
    {
      "name": "ROSS STORES INC",
      "ticker": "ROST",
      "weight": 0.124732,
      "shares_held": 3809264
    },
    {
      "name": "ROYAL CARIBBEAN CRUISES LTD",
      "ticker": "RCL",
      "weight": 0.1207,
      "shares_held": 2962923
    },
    {
      "name": "RTX CORP",
      "ticker": "RTX",
      "weight": 0.469812,
      "shares_held": 15827868
    },
    {
      "name": "S+P GLOBAL INC",
      "ticker": "SPGI",
      "weight": 0.229894,
      "shares_held": 3606671
    },
    {
      "name": "SALESFORCE INC",
      "ticker": "CRM",
      "weight": 0.283498,
      "shares_held": 11046640
    },
    {
      "name": "SANDISK CORP",
      "ticker": "SNDK",
      "weight": 0.198766,
      "shares_held": 1744889
    },
    {
      "name": "SBA COMMUNICATIONS CORP",
      "ticker": "SBAC",
      "weight": 0.040226,
      "shares_held": 1260843
    },
    {
      "name": "SCHWAB (CHARLES) CORP",
      "ticker": "SCHW",
      "weight": 0.27831,
      "shares_held": 19729783
    },
    {
      "name": "SEAGATE TECHNOLOGY HOLDINGS",
      "ticker": "STX",
      "weight": 0.186658,
      "shares_held": 2578241
    },
    {
      "name": "SEMPRA",
      "ticker": "SRE",
      "weight": 0.111228,
      "shares_held": 7711277
    },
    {
      "name": "SERVICENOW INC",
      "ticker": "NOW",
      "weight": 0.175439,
      "shares_held": 12338892
    },
    {
      "name": "SHERWIN WILLIAMS CO/THE",
      "ticker": "SHW",
      "weight": 0.133582,
      "shares_held": 2728070
    },
    {
      "name": "SIMON PROPERTY GROUP INC",
      "ticker": "SPG",
      "weight": 0.108397,
      "shares_held": 3829527
    },
    {
      "name": "SKYWORKS SOLUTIONS INC",
      "ticker": "SWKS",
      "weight": 0.014827,
      "shares_held": 1797684
    },
    {
      "name": "SLB LTD",
      "ticker": "SLB",
      "weight": 0.13361,
      "shares_held": 17654707
    },
    {
      "name": "SMITH (A.O.) CORP",
      "ticker": "AOS",
      "weight": 0.012969,
      "shares_held": 1331490
    },
    {
      "name": "SMURFIT WESTROCK PLC",
      "ticker": "SW",
      "weight": 0.038058,
      "shares_held": 6170590
    },
    {
      "name": "SNAP ON INC",
      "ticker": "SNA",
      "weight": 0.034075,
      "shares_held": 613719
    },
    {
      "name": "SOLVENTUM CORP",
      "ticker": "SOLV",
      "weight": 0.016681,
      "shares_held": 1752494
    },
    {
      "name": "SOUTHERN CO/THE",
      "ticker": "SO",
      "weight": 0.183921,
      "shares_held": 12975387
    },
    {
      "name": "SOUTHWEST AIRLINES CO",
      "ticker": "LUV",
      "weight": 0.033969,
      "shares_held": 5764000
    },
    {
      "name": "STANLEY BLACK + DECKER INC",
      "ticker": "SWK",
      "weight": 0.019193,
      "shares_held": 1840382
    },
    {
      "name": "STARBUCKS CORP",
      "ticker": "SBUX",
      "weight": 0.190373,
      "shares_held": 13425010
    },
    {
      "name": "STATE STREET CORP",
      "ticker": "STT",
      "weight": 0.065627,
      "shares_held": 3304818
    },
    {
      "name": "STEEL DYNAMICS INC",
      "ticker": "STLD",
      "weight": 0.044446,
      "shares_held": 1624492
    },
    {
      "name": "STERIS PLC",
      "ticker": "STE",
      "weight": 0.038129,
      "shares_held": 1161535
    },
    {
      "name": "STRYKER CORP",
      "ticker": "SYK",
      "weight": 0.201571,
      "shares_held": 4064033
    },
    {
      "name": "SUPER MICRO COMPUTER INC",
      "ticker": "SMCI",
      "weight": 0.0202,
      "shares_held": 5925462
    },
    {
      "name": "SYNCHRONY FINANCIAL",
      "ticker": "SYF",
      "weight": 0.042839,
      "shares_held": 4080477
    },
    {
      "name": "SYNOPSYS INC",
      "ticker": "SNPS",
      "weight": 0.135025,
      "shares_held": 2256731
    },
    {
      "name": "SYSCO CORP",
      "ticker": "SYY",
      "weight": 0.061923,
      "shares_held": 5648602
    },
    {
      "name": "T MOBILE US INC",
      "ticker": "TMUS",
      "weight": 0.160956,
      "shares_held": 5583088
    },
    {
      "name": "T ROWE PRICE GROUP INC",
      "ticker": "TROW",
      "weight": 0.034777,
      "shares_held": 2596677
    },
    {
      "name": "TAKE TWO INTERACTIVE SOFTWRE",
      "ticker": "TTWO",
      "weight": 0.060486,
      "shares_held": 2051389
    },
    {
      "name": "TAPESTRY INC",
      "ticker": "TPR",
      "weight": 0.05226,
      "shares_held": 2379319
    },
    {
      "name": "TARGA RESOURCES CORP",
      "ticker": "TRGP",
      "weight": 0.090086,
      "shares_held": 2530981
    },
    {
      "name": "TARGET CORP",
      "ticker": "TGT",
      "weight": 0.095725,
      "shares_held": 5329902
    },
    {
      "name": "TE CONNECTIVITY PLC",
      "ticker": "TEL",
      "weight": 0.112408,
      "shares_held": 3455064
    },
    {
      "name": "TELEDYNE TECHNOLOGIES INC",
      "ticker": "TDY",
      "weight": 0.053216,
      "shares_held": 552476
    },
    {
      "name": "TERADYNE INC",
      "ticker": "TER",
      "weight": 0.096865,
      "shares_held": 1853336
    },
    {
      "name": "TESLA INC",
      "ticker": "TSLA",
      "weight": 1.661639,
      "shares_held": 33185360
    },
    {
      "name": "TEXAS INSTRUMENTS INC",
      "ticker": "TXN",
      "weight": 0.326034,
      "shares_held": 10699024
    },
    {
      "name": "TEXAS PACIFIC LAND CORP",
      "ticker": "TPL",
      "weight": 0.04469,
      "shares_held": 683408
    },
    {
      "name": "TEXTRON INC",
      "ticker": "TXT",
      "weight": 0.027186,
      "shares_held": 2039670
    },
    {
      "name": "THE CAMPBELL S COMPANY",
      "ticker": "CPB",
      "weight": 0.00707,
      "shares_held": 2342455
    },
    {
      "name": "THE CIGNA GROUP",
      "ticker": "CI",
      "weight": 0.125633,
      "shares_held": 3102892
    },
    {
      "name": "THERMO FISHER SCIENTIFIC INC",
      "ticker": "TMO",
      "weight": 0.325304,
      "shares_held": 4429402
    },
    {
      "name": "TJX COMPANIES INC",
      "ticker": "TJX",
      "weight": 0.30868,
      "shares_held": 13091219
    },
    {
      "name": "TKO GROUP HOLDINGS INC",
      "ticker": "TKO",
      "weight": 0.022548,
      "shares_held": 784412
    },
    {
      "name": "TRACTOR SUPPLY COMPANY",
      "ticker": "TSCO",
      "weight": 0.041391,
      "shares_held": 6266485
    },
    {
      "name": "TRADE DESK INC/THE  CLASS A",
      "ticker": "TTD",
      "weight": 0.01539,
      "shares_held": 5210035
    },
    {
      "name": "TRANE TECHNOLOGIES PLC",
      "ticker": "TT",
      "weight": 0.170996,
      "shares_held": 2607992
    },
    {
      "name": "TRANSDIGM GROUP INC",
      "ticker": "TDG",
      "weight": 0.118492,
      "shares_held": 665875
    },
    {
      "name": "TRAVELERS COS INC/THE",
      "ticker": "TRV",
      "weight": 0.112034,
      "shares_held": 2546548
    },
    {
      "name": "TRIMBLE INC",
      "ticker": "TRMB",
      "weight": 0.027262,
      "shares_held": 2800201
    },
    {
      "name": "TRUIST FINANCIAL CORP",
      "ticker": "TFC",
      "weight": 0.106866,
      "shares_held": 14862783
    },
    {
      "name": "TYLER TECHNOLOGIES INC",
      "ticker": "TYL",
      "weight": 0.024354,
      "shares_held": 509179
    },
    {
      "name": "TYSON FOODS INC CL A",
      "ticker": "TSN",
      "weight": 0.031583,
      "shares_held": 3348955
    },
    {
      "name": "UBER TECHNOLOGIES INC",
      "ticker": "UBER",
      "weight": 0.256159,
      "shares_held": 24261171
    },
    {
      "name": "UDR INC",
      "ticker": "UDR",
      "weight": 0.018331,
      "shares_held": 3588301
    },
    {
      "name": "ULTA BEAUTY INC",
      "ticker": "ULTA",
      "weight": 0.040492,
      "shares_held": 520964
    },
    {
      "name": "UNION PACIFIC CORP",
      "ticker": "UNP",
      "weight": 0.254652,
      "shares_held": 7007715
    },
    {
      "name": "UNITED AIRLINES HOLDINGS INC",
      "ticker": "UAL",
      "weight": 0.053779,
      "shares_held": 3828297
    },
    {
      "name": "UNITED PARCEL SERVICE CL B",
      "ticker": "UPS",
      "weight": 0.127936,
      "shares_held": 8730954
    },
    {
      "name": "UNITED RENTALS INC",
      "ticker": "URI",
      "weight": 0.082283,
      "shares_held": 741519
    },
    {
      "name": "UNITEDHEALTH GROUP INC",
      "ticker": "UNH",
      "weight": 0.476748,
      "shares_held": 10681109
    },
    {
      "name": "UNIVERSAL HEALTH SERVICES B",
      "ticker": "UHS",
      "weight": 0.017611,
      "shares_held": 646415
    },
    {
      "name": "US BANCORP",
      "ticker": "USB",
      "weight": 0.148295,
      "shares_held": 18363267
    },
    {
      "name": "US DOLLAR",
      "ticker": "-",
      "weight": 0.259691,
      "shares_held": 1780235636.31
    },
    {
      "name": "VALERO ENERGY CORP",
      "ticker": "VLO",
      "weight": 0.125601,
      "shares_held": 3592983
    },
    {
      "name": "VENTAS INC",
      "ticker": "VTR",
      "weight": 0.068695,
      "shares_held": 5602809
    },
    {
      "name": "VERALTO CORP",
      "ticker": "VLTO",
      "weight": 0.038918,
      "shares_held": 2948942
    },
    {
      "name": "VERISIGN INC",
      "ticker": "VRSN",
      "weight": 0.038258,
      "shares_held": 968140
    },
    {
      "name": "VERISK ANALYTICS INC",
      "ticker": "VRSK",
      "weight": 0.042296,
      "shares_held": 1652792
    },
    {
      "name": "VERIZON COMMUNICATIONS INC",
      "ticker": "VZ",
      "weight": 0.348424,
      "shares_held": 49719324
    },
    {
      "name": "VERTEX PHARMACEUTICALS INC",
      "ticker": "VRTX",
      "weight": 0.194427,
      "shares_held": 3002418
    },
    {
      "name": "VERTIV HOLDINGS CO A",
      "ticker": "VRT",
      "weight": 0.18501,
      "shares_held": 4512973
    },
    {
      "name": "VIATRIS INC",
      "ticker": "VTRS",
      "weight": 0.027072,
      "shares_held": 13676060
    },
    {
      "name": "VICI PROPERTIES INC",
      "ticker": "VICI",
      "weight": 0.050857,
      "shares_held": 12572547
    },
    {
      "name": "VISA INC CLASS A SHARES",
      "ticker": "V",
      "weight": 0.8941,
      "shares_held": 19838298
    },
    {
      "name": "VISTRA CORP",
      "ticker": "VST",
      "weight": 0.085715,
      "shares_held": 3769297
    },
    {
      "name": "VULCAN MATERIALS CO",
      "ticker": "VMC",
      "weight": 0.066572,
      "shares_held": 1559801
    },
    {
      "name": "WABTEC CORP",
      "ticker": "WAB",
      "weight": 0.079344,
      "shares_held": 2017048
    },
    {
      "name": "WALMART INC",
      "ticker": "WMT",
      "weight": 0.960301,
      "shares_held": 51729201
    },
    {
      "name": "WALT DISNEY CO/THE",
      "ticker": "DIS",
      "weight": 0.302151,
      "shares_held": 20884342
    },
    {
      "name": "WARNER BROS DISCOVERY INC",
      "ticker": "WBD",
      "weight": 0.117724,
      "shares_held": 29293120
    },
    {
      "name": "WASTE MANAGEMENT INC",
      "ticker": "WM",
      "weight": 0.148108,
      "shares_held": 4387114
    },
    {
      "name": "WATERS CORP",
      "ticker": "WAT",
      "weight": 0.053563,
      "shares_held": 1152748.316
    },
    {
      "name": "WEC ENERGY GROUP INC",
      "ticker": "WEC",
      "weight": 0.065847,
      "shares_held": 3848885
    },
    {
      "name": "WELLS FARGO + CO",
      "ticker": "WFC",
      "weight": 0.450329,
      "shares_held": 36464644
    },
    {
      "name": "WELLTOWER INC",
      "ticker": "WELL",
      "weight": 0.245786,
      "shares_held": 8231124
    },
    {
      "name": "WEST PHARMACEUTICAL SERVICES",
      "ticker": "WST",
      "weight": 0.033025,
      "shares_held": 851334
    },
    {
      "name": "WESTERN DIGITAL CORP",
      "ticker": "WDC",
      "weight": 0.197441,
      "shares_held": 3995221
    },
    {
      "name": "WEYERHAEUSER CO",
      "ticker": "WY",
      "weight": 0.030947,
      "shares_held": 8520053
    },
    {
      "name": "WILLIAMS COS INC",
      "ticker": "WMB",
      "weight": 0.15324,
      "shares_held": 14388341
    },
    {
      "name": "WILLIAMS SONOMA INC",
      "ticker": "WSM",
      "weight": 0.038323,
      "shares_held": 1400913
    },
    {
      "name": "WILLIS TOWERS WATSON PLC",
      "ticker": "WTW",
      "weight": 0.047383,
      "shares_held": 1116911
    },
    {
      "name": "WORKDAY INC CLASS A",
      "ticker": "WDAY",
      "weight": 0.043511,
      "shares_held": 2502933
    },
    {
      "name": "WR BERKLEY CORP",
      "ticker": "WRB",
      "weight": 0.034271,
      "shares_held": 3494963
    },
    {
      "name": "WW GRAINGER INC",
      "ticker": "GWW",
      "weight": 0.086597,
      "shares_held": 517686
    },
    {
      "name": "WYNN RESORTS LTD",
      "ticker": "WYNN",
      "weight": 0.015274,
      "shares_held": 994911
    },
    {
      "name": "XCEL ENERGY INC",
      "ticker": "XEL",
      "weight": 0.083139,
      "shares_held": 6996462
    },
    {
      "name": "XYLEM INC",
      "ticker": "XYL",
      "weight": 0.053593,
      "shares_held": 2870903
    },
    {
      "name": "YUM  BRANDS INC",
      "ticker": "YUM",
      "weight": 0.076826,
      "shares_held": 3282778
    },
    {
      "name": "ZEBRA TECHNOLOGIES CORP CL A",
      "ticker": "ZBRA",
      "weight": 0.018522,
      "shares_held": 574173
    },
    {
      "name": "ZIMMER BIOMET HOLDINGS INC",
      "ticker": "ZBH",
      "weight": 0.031817,
      "shares_held": 2345051
    },
    {
      "name": "ZOETIS INC",
      "ticker": "ZTS",
      "weight": 0.086793,
      "shares_held": 4968559
    }
  ],
  "number_of_holdings": "503",
  "premium_discount": "0.01%",
  "price": 676.01,
  "price_book_ratio": "5.01",
  "price_cash_flow": "18.45",
  "price_earnings": "26.96",
  "price_earnings_fw": "21.57",
  "ticker": "SPY",
  "weighted_average_market_cap": "$1,290,463.80 M"
}
