{
  "date": "2026-05-04",
  "holdings": [
    {
      "name": "ADVANCED MICRO DEVICES",
      "ticker": "AMD",
      "weight": 3.056767,
      "shares_held": 235267
    },
    {
      "name": "ALLEGRO MICROSYSTEMS INC",
      "ticker": "ALGM",
      "weight": 2.750479,
      "shares_held": 1461231
    },
    {
      "name": "ALPHA + OMEGA SEMICONDUCTOR",
      "ticker": "AOSL",
      "weight": 0.816914,
      "shares_held": 509108
    },
    {
      "name": "AMBARELLA INC",
      "ticker": "AMBA",
      "weight": 2.406645,
      "shares_held": 894561
    },
    {
      "name": "ANALOG DEVICES INC",
      "ticker": "ADI",
      "weight": 2.285221,
      "shares_held": 151306
    },
    {
      "name": "ASTERA LABS INC",
      "ticker": "ALAB",
      "weight": 2.965547,
      "shares_held": 387355
    },
    {
      "name": "BROADCOM INC",
      "ticker": "AVGO",
      "weight": 2.24071,
      "shares_held": 141420
    },
    {
      "name": "CEVA INC",
      "ticker": "CEVA",
      "weight": 0.907484,
      "shares_held": 733323
    },
    {
      "name": "CIRRUS LOGIC INC",
      "ticker": "CRUS",
      "weight": 2.228487,
      "shares_held": 356826
    },
    {
      "name": "CONTRA DATAVAULT AI IN",
      "ticker": "-",
      "weight": 0,
      "shares_held": 147739
    },
    {
      "name": "CREDO TECHNOLOGY GROUP HOLDI",
      "ticker": "CRDO",
      "weight": 2.854963,
      "shares_held": 416796
    },
    {
      "name": "DIODES INC",
      "ticker": "DIOD",
      "weight": 2.100878,
      "shares_held": 508056
    },
    {
      "name": "FIRST SOLAR INC",
      "ticker": "FSLR",
      "weight": 1.939851,
      "shares_held": 241226
    },
    {
      "name": "IMPINJ INC",
      "ticker": "PI",
      "weight": 2.655156,
      "shares_held": 487470
    },
    {
      "name": "INDIE SEMICONDUCTOR INC A",
      "ticker": "INDI",
      "weight": 1.274262,
      "shares_held": 7682676
    },
    {
      "name": "INTEL CORP",
      "ticker": "INTC",
      "weight": 3.668435,
      "shares_held": 1006807
    },
    {
      "name": "KOPIN CORP",
      "ticker": "KOPN",
      "weight": 0.817976,
      "shares_held": 4810312
    },
    {
      "name": "LATTICE SEMICONDUCTOR CORP",
      "ticker": "LSCC",
      "weight": 2.535384,
      "shares_held": 530760
    },
    {
      "name": "MACOM TECHNOLOGY SOLUTIONS H",
      "ticker": "MTSI",
      "weight": 2.403601,
      "shares_held": 216589
    },
    {
      "name": "MARVELL TECHNOLOGY INC",
      "ticker": "MRVL",
      "weight": 3.325292,
      "shares_held": 534106
    },
    {
      "name": "MAXLINEAR INC",
      "ticker": "MXL",
      "weight": 6.475166,
      "shares_held": 2178858
    },
    {
      "name": "MICROCHIP TECHNOLOGY INC",
      "ticker": "MCHP",
      "weight": 2.662049,
      "shares_held": 734283
    },
    {
      "name": "MICRON TECHNOLOGY INC",
      "ticker": "MU",
      "weight": 2.52992,
      "shares_held": 115368
    },
    {
      "name": "MONOLITHIC POWER SYSTEMS INC",
      "ticker": "MPWR",
      "weight": 2.692935,
      "shares_held": 44994
    },
    {
      "name": "NAVITAS SEMICONDUCTOR CORP",
      "ticker": "NVTS",
      "weight": 2.674543,
      "shares_held": 4416181
    },
    {
      "name": "NVE CORP",
      "ticker": "NVEC",
      "weight": 0.26022,
      "shares_held": 81501
    },
    {
      "name": "NVIDIA CORP",
      "ticker": "NVDA",
      "weight": 1.960815,
      "shares_held": 259693
    },
    {
      "name": "NXP SEMICONDUCTORS NV",
      "ticker": "NXPI",
      "weight": 2.666873,
      "shares_held": 241106
    },
    {
      "name": "ON SEMICONDUCTOR",
      "ticker": "ON",
      "weight": 3.158168,
      "shares_held": 813589
    },
    {
      "name": "PENGUIN SOLUTIONS INC",
      "ticker": "PENG",
      "weight": 1.778781,
      "shares_held": 1443171
    },
    {
      "name": "POWER INTEGRATIONS INC",
      "ticker": "POWI",
      "weight": 2.857486,
      "shares_held": 1031086
    },
    {
      "name": "QORVO INC",
      "ticker": "QRVO",
      "weight": 2.162464,
      "shares_held": 614337
    },
    {
      "name": "QUALCOMM INC",
      "ticker": "QCOM",
      "weight": 2.301597,
      "shares_held": 359318
    },
    {
      "name": "RAMBUS INC",
      "ticker": "RMBS",
      "weight": 2.209423,
      "shares_held": 520888
    },
    {
      "name": "RIGETTI COMPUTING INC",
      "ticker": "RGTI",
      "weight": 1.920115,
      "shares_held": 2851637
    },
    {
      "name": "SEMTECH CORP",
      "ticker": "SMTC",
      "weight": 2.293277,
      "shares_held": 562869
    },
    {
      "name": "SILICON LABORATORIES INC",
      "ticker": "SLAB",
      "weight": 1.977017,
      "shares_held": 239492
    },
    {
      "name": "SITIME CORP",
      "ticker": "SITM",
      "weight": 2.957062,
      "shares_held": 137657
    },
    {
      "name": "SKYWATER TECHNOLOGY INC",
      "ticker": "SKYT",
      "weight": 0.969794,
      "shares_held": 791952
    },
    {
      "name": "SKYWORKS SOLUTIONS INC",
      "ticker": "SWKS",
      "weight": 2.280734,
      "shares_held": 870785
    },
    {
      "name": "SSI US GOV MONEY MARKET CLASS",
      "ticker": "-",
      "weight": 0.05005,
      "shares_held": 1315656.47
    },
    {
      "name": "SYNAPTICS INC",
      "ticker": "SYNA",
      "weight": 2.416171,
      "shares_held": 630097
    },
    {
      "name": "TEXAS INSTRUMENTS INC",
      "ticker": "TXN",
      "weight": 2.585041,
      "shares_held": 243149
    },
    {
      "name": "UNIVERSAL DISPLAY CORP",
      "ticker": "OLED",
      "weight": 1.802303,
      "shares_held": 490649
    },
    {
      "name": "US DOLLAR",
      "ticker": "-",
      "weight": -0.000157,
      "shares_held": -4117.16
    },
    {
      "name": "WOLFSPEED INC",
      "ticker": "WOLF",
      "weight": 1.129095,
      "shares_held": 825834
    }
  ],
  "ticker": "XSD"
}
